{"На Калинина":{"@attributes":{"Code":"PRS1","Status":"ACTIVE","PostalCode":"188760","Name":"На Калинина","CountryCode":"1","countryCodeIso":"RU","CountryName":"Россия","RegionCode":"26","RegionName":"Ленинградская обл.","CityCode":"84","City":"Приозерск","WorkTime":"Пн-Пт 10:00-19:00, Сб 10:00-16:00","Address":"ул. Калинина, 51","FullAddress":"Россия, Ленинградская обл., Приозерск, ул. Калинина, 51","AddressComment":"Остановка на Калинина 49, дойти до МФЦ, вход с дальнего торца здания под лестницей.","Phone":"+79633210962","Email":"M.Martynov@cdek.ru","Note":"Остановка на Калинина 49, дойти до МФЦ, вход с дальнего торца здания под лестницей.","coordX":"30.147003","coordY":"61.038907","Type":"PVZ","ownerCode":"cdek","IsDressingRoom":"true","HaveCashless":"true","HaveCash":"true","AllowedCod":"true","TakeOnly":"false","IsHandout":"true","IsReception":"true","NearestStation":"Улица Калинина 49","MetroStation":"","Site":"","Fulfillment":"false","FiasGuid":"59a9c284-72fb-49e6-8380-10ca044d0bd7"},"PhoneDetail":{"@attributes":{"number":"+79633210962"}},"OfficeImage":[{"@attributes":{"url":"edu.api-pvz.imageRepository.service.cdek.tech:8008\/images\/2149\/2165_3_PRS1"}},{"@attributes":{"url":"edu.api-pvz.imageRepository.service.cdek.tech:8008\/images\/2149\/2163_1_PRS1"}},{"@attributes":{"url":"edu.api-pvz.imageRepository.service.cdek.tech:8008\/images\/2149\/2164_2_PRS1"}}],"WorkTimeY":[{"@attributes":{"day":"1","periods":"10:00\/19:00"}},{"@attributes":{"day":"2","periods":"10:00\/19:00"}},{"@attributes":{"day":"3","periods":"10:00\/19:00"}},{"@attributes":{"day":"4","periods":"10:00\/19:00"}},{"@attributes":{"day":"5","periods":"10:00\/19:00"}},{"@attributes":{"day":"6","periods":"10:00\/16:00"}}]}}