{"6101 Постамат ОМНИСДЭК":{"@attributes":{"Code":"CHT6","Status":"ACTIVE","PostalCode":"672000","Name":"6101 Постамат ОМНИСДЭК","CountryCode":"1","countryCodeIso":"RU","CountryName":"Россия","RegionCode":"49","RegionName":"Забайкальский край","CityCode":"231","City":"Чита","WorkTime":"Пн-Вс 09:00-20:00","Address":"ул. Журавлева, 20","FullAddress":"Россия, Забайкальский край, Чита, ул. Журавлева, 20","AddressComment":"","Phone":"+78007753553","Note":"","coordX":"113.496818","coordY":"52.034694","Type":"POSTAMAT","ownerCode":"cdek","IsDressingRoom":"false","HaveCashless":"true","HaveCash":"false","AllowedCod":"true","TakeOnly":"false","IsHandout":"true","IsReception":"true","NearestStation":"Магазин Скороход","MetroStation":"","Site":"","Fulfillment":"false","FiasGuid":"2d9abaa6-85a6-4f1f-a1bd-14b76ec17d9c"},"PhoneDetail":{"@attributes":{"number":"+78007753553"}},"OfficeImage":[{"@attributes":{"url":"https:\/\/pvzimage.cdek.ru\/images\/6722\/21963_image"}},{"@attributes":{"url":"https:\/\/pvzimage.cdek.ru\/images\/6722\/21965_image"}},{"@attributes":{"url":"https:\/\/pvzimage.cdek.ru\/images\/6722\/21967_image"}}],"WorkTimeY":[{"@attributes":{"day":"1","periods":"09:00\/20:00"}},{"@attributes":{"day":"2","periods":"09:00\/20:00"}},{"@attributes":{"day":"3","periods":"09:00\/20:00"}},{"@attributes":{"day":"4","periods":"09:00\/20:00"}},{"@attributes":{"day":"5","periods":"09:00\/20:00"}},{"@attributes":{"day":"6","periods":"09:00\/20:00"}},{"@attributes":{"day":"7","periods":"09:00\/20:00"}}],"WeightLimit":{"@attributes":{"WeightMin":"0","WeightMax":"30"}},"Dimensions":{"@attributes":{"depth":"40.5","height":"36.5","width":"64.5"}}},"На Малой, 4 стр.1":{"@attributes":{"Code":"CHT3","Status":"ACTIVE","PostalCode":"672007","Name":"На Малой, 4 стр.1","CountryCode":"1","countryCodeIso":"RU","CountryName":"Россия","RegionCode":"49","RegionName":"Забайкальский край","CityCode":"231","City":"Чита","WorkTime":"Пн-Пт 09:00-20:00, Сб-Вс 10:00-18:00","Address":"ул. Малая, 4 стр. 1","FullAddress":"Россия, Забайкальский край, Чита, ул. Малая, 4 стр. 1","AddressComment":"остановка Малая улица, маршрутное такси №42,48,57 Рядом общежитие, детский сад №27","Phone":"+79144980756","Email":"dir-chita@cdek.ru","Note":"остановка Малая улица, маршрутное такси №42,48,57 Рядом общежитие, детский сад №27","coordX":"113.482751","coordY":"52.034018","Type":"PVZ","ownerCode":"cdek","IsDressingRoom":"true","HaveCashless":"true","HaveCash":"true","AllowedCod":"true","TakeOnly":"false","IsHandout":"true","IsReception":"true","NearestStation":"магазин \"Сделай сам\"","MetroStation":"","Site":"","Fulfillment":"false","FiasGuid":"2d9abaa6-85a6-4f1f-a1bd-14b76ec17d9c"},"PhoneDetail":{"@attributes":{"number":"+79144980756"}},"OfficeImage":[{"@attributes":{"url":"https:\/\/pvzimage.cdek.ru\/images\/2314\/37169_image"}},{"@attributes":{"url":"https:\/\/pvzimage.cdek.ru\/images\/2314\/37177_image"}},{"@attributes":{"url":"https:\/\/pvzimage.cdek.ru\/images\/2314\/37171_image"}},{"@attributes":{"url":"https:\/\/pvzimage.cdek.ru\/images\/2314\/37173_image"}},{"@attributes":{"url":"https:\/\/pvzimage.cdek.ru\/images\/2314\/37175_image"}}],"WorkTimeY":[{"@attributes":{"day":"1","periods":"09:00\/20:00"}},{"@attributes":{"day":"2","periods":"09:00\/20:00"}},{"@attributes":{"day":"3","periods":"09:00\/20:00"}},{"@attributes":{"day":"4","periods":"09:00\/20:00"}},{"@attributes":{"day":"5","periods":"09:00\/20:00"}},{"@attributes":{"day":"6","periods":"10:00\/18:00"}},{"@attributes":{"day":"7","periods":"10:00\/18:00"}}]},"6100 Постамат ОМНИСДЭК":{"@attributes":{"Code":"CHT7","Status":"ACTIVE","PostalCode":"672012","Name":"6100 Постамат ОМНИСДЭК","CountryCode":"1","countryCodeIso":"RU","CountryName":"Россия","RegionCode":"49","RegionName":"Забайкальский край","CityCode":"231","City":"Чита","WorkTime":"Пн-Вс 08:00-23:00","Address":"ул. Новобульварная, 55","FullAddress":"Россия, Забайкальский край, Чита, ул. Новобульварная, 55","AddressComment":"ТЦ Абсолют","Phone":"+78007753553","Note":"ТЦ Абсолют","coordX":"113.504005","coordY":"52.047224","Type":"POSTAMAT","ownerCode":"cdek","IsDressingRoom":"false","HaveCashless":"true","HaveCash":"false","AllowedCod":"true","TakeOnly":"false","IsHandout":"true","IsReception":"true","NearestStation":"Машзавод","MetroStation":"","Site":"","Fulfillment":"false","FiasGuid":"2d9abaa6-85a6-4f1f-a1bd-14b76ec17d9c"},"PhoneDetail":{"@attributes":{"number":"+78007753553"}},"OfficeImage":[{"@attributes":{"url":"https:\/\/pvzimage.cdek.ru\/images\/6868\/21955_image"}},{"@attributes":{"url":"https:\/\/pvzimage.cdek.ru\/images\/6868\/21957_image"}},{"@attributes":{"url":"https:\/\/pvzimage.cdek.ru\/images\/6868\/21961_image"}},{"@attributes":{"url":"https:\/\/pvzimage.cdek.ru\/images\/6868\/21959_image"}}],"WorkTimeY":[{"@attributes":{"day":"1","periods":"08:00\/23:00"}},{"@attributes":{"day":"2","periods":"08:00\/23:00"}},{"@attributes":{"day":"3","periods":"08:00\/23:00"}},{"@attributes":{"day":"4","periods":"08:00\/23:00"}},{"@attributes":{"day":"5","periods":"08:00\/23:00"}},{"@attributes":{"day":"6","periods":"08:00\/23:00"}},{"@attributes":{"day":"7","periods":"08:00\/23:00"}}],"WeightLimit":{"@attributes":{"WeightMin":"0","WeightMax":"30"}},"Dimensions":{"@attributes":{"depth":"40.5","height":"36.5","width":"64.5"}}},"На 9 Января, 20":{"@attributes":{"Code":"CHT4","Status":"ACTIVE","PostalCode":"672039","Name":"На 9 Января, 20","CountryCode":"1","countryCodeIso":"RU","CountryName":"Россия","RegionCode":"49","RegionName":"Забайкальский край","CityCode":"231","City":"Чита","WorkTime":"Пн-Пт 10:00-20:00, Сб-Вс 10:00-18:00","Address":"ул. 9 Января, 20 пом. 23","FullAddress":"Россия, Забайкальский край, Чита, ул. 9 Января, 20 пом. 23","AddressComment":"1 этаж, напротив ТЦ \"Экран\"","Phone":"+79243885605, +79744980756","Email":"dir-chita@cdek.ru","Note":"1 этаж, напротив ТЦ \"Экран\"","coordX":"113.509062","coordY":"52.028538","Type":"PVZ","ownerCode":"cdek","IsDressingRoom":"true","HaveCashless":"true","HaveCash":"true","AllowedCod":"true","TakeOnly":"false","IsHandout":"true","IsReception":"true","NearestStation":"М-н Угловой, Театральная площадь, Дом офицеров","MetroStation":"","Site":"","Fulfillment":"false","FiasGuid":"2d9abaa6-85a6-4f1f-a1bd-14b76ec17d9c"},"PhoneDetail":[{"@attributes":{"number":"+79243885605"}},{"@attributes":{"number":"+79744980756"}}],"OfficeImage":[{"@attributes":{"url":"https:\/\/pvzimage.cdek.ru\/images\/3943\/30677_image"}},{"@attributes":{"url":"https:\/\/pvzimage.cdek.ru\/images\/3943\/30683_image"}},{"@attributes":{"url":"https:\/\/pvzimage.cdek.ru\/images\/3943\/30679_image"}},{"@attributes":{"url":"https:\/\/pvzimage.cdek.ru\/images\/3943\/30689_image"}},{"@attributes":{"url":"https:\/\/pvzimage.cdek.ru\/images\/3943\/30681_image"}},{"@attributes":{"url":"https:\/\/pvzimage.cdek.ru\/images\/3943\/30693_image"}},{"@attributes":{"url":"https:\/\/pvzimage.cdek.ru\/images\/3943\/30685_image"}},{"@attributes":{"url":"https:\/\/pvzimage.cdek.ru\/images\/3943\/30691_image"}}],"WorkTimeY":[{"@attributes":{"day":"1","periods":"10:00\/20:00"}},{"@attributes":{"day":"2","periods":"10:00\/20:00"}},{"@attributes":{"day":"3","periods":"10:00\/20:00"}},{"@attributes":{"day":"4","periods":"10:00\/20:00"}},{"@attributes":{"day":"5","periods":"10:00\/20:00"}},{"@attributes":{"day":"6","periods":"10:00\/18:00"}},{"@attributes":{"day":"7","periods":"10:00\/18:00"}}],"WeightLimit":{"@attributes":{"WeightMin":"0","WeightMax":"35"}}},"На Богомягкова, 55":{"@attributes":{"Code":"CHT9","Status":"ACTIVE","PostalCode":"672007","Name":"На Богомягкова, 55","CountryCode":"1","countryCodeIso":"RU","CountryName":"Россия","RegionCode":"49","RegionName":"Забайкальский край","CityCode":"231","City":"Чита","WorkTime":"Пн-Пт 09:00-20:00, Сб-Вс 10:00-18:00","Address":"ул. Богогомягкова, 55, пом. 4","FullAddress":"Россия, Забайкальский край, Чита, ул. Богогомягкова, 55, пом. 4","AddressComment":"Остановка \"Центральный рынок\", магазин \"Маркет\"","Phone":"+73022350367","Email":"dir-chita@cdek.ru","Note":"Остановка \"Центральный рынок\", магазин \"Маркет\"","coordX":"113.498112","coordY":"52.04466","Type":"PVZ","ownerCode":"cdek","IsDressingRoom":"true","HaveCashless":"true","HaveCash":"true","AllowedCod":"true","TakeOnly":"false","IsHandout":"true","IsReception":"true","NearestStation":"Центральный рынок, Магазин Маркет","MetroStation":"","Site":"","Fulfillment":"false","FiasGuid":"2d9abaa6-85a6-4f1f-a1bd-14b76ec17d9c"},"PhoneDetail":{"@attributes":{"number":"+73022350367"}},"OfficeImage":[{"@attributes":{"url":"https:\/\/pvzimage.cdek.ru\/images\/8528\/36273_image"}},{"@attributes":{"url":"https:\/\/pvzimage.cdek.ru\/images\/8528\/36275_image"}},{"@attributes":{"url":"https:\/\/pvzimage.cdek.ru\/images\/8528\/36277_image"}},{"@attributes":{"url":"https:\/\/pvzimage.cdek.ru\/images\/8528\/36279_image"}},{"@attributes":{"url":"https:\/\/pvzimage.cdek.ru\/images\/8528\/36281_image"}}],"WorkTimeY":[{"@attributes":{"day":"1","periods":"09:00\/20:00"}},{"@attributes":{"day":"2","periods":"09:00\/20:00"}},{"@attributes":{"day":"3","periods":"09:00\/20:00"}},{"@attributes":{"day":"4","periods":"09:00\/20:00"}},{"@attributes":{"day":"5","periods":"09:00\/20:00"}},{"@attributes":{"day":"6","periods":"10:00\/18:00"}},{"@attributes":{"day":"7","periods":"10:00\/18:00"}}],"WeightLimit":{"@attributes":{"WeightMin":"0","WeightMax":"120"}}},"Северный":{"@attributes":{"Code":"CHT5","Status":"ACTIVE","PostalCode":"672049","Name":"Северный","CountryCode":"1","countryCodeIso":"RU","CountryName":"Россия","RegionCode":"49","RegionName":"Забайкальский край","CityCode":"231","City":"Чита","WorkTime":"Пн-Пт 10:00-20:00, Сб-Вс 10:00-18:00","Address":"ул. Виля Липатова, 22 цокольный этаж","FullAddress":"Россия, Забайкальский край, Чита, ул. Виля Липатова, 22 цокольный этаж","AddressComment":"Дом Быта\" на Липатова, цокольный этаж, рядом поликлиника №1(300м), магазин \"Янта\" (200м)","Phone":"+79248084477","Email":"dir-chita@cdek.ru","Note":"Дом Быта\" на Липатова, цокольный этаж, рядом поликлиника №1(300м), магазин \"Янта\" (200м)","coordX":"113.48708","coordY":"52.071843","Type":"PVZ","ownerCode":"cdek","IsDressingRoom":"true","HaveCashless":"true","HaveCash":"true","AllowedCod":"true","TakeOnly":"false","IsHandout":"true","IsReception":"true","NearestStation":"\"Поликлиника\"","MetroStation":"","Site":"","Fulfillment":"false","FiasGuid":"2d9abaa6-85a6-4f1f-a1bd-14b76ec17d9c"},"PhoneDetail":{"@attributes":{"number":"+79248084477"}},"OfficeImage":[{"@attributes":{"url":"https:\/\/pvzimage.cdek.ru\/images\/5477\/12570_image"}},{"@attributes":{"url":"https:\/\/pvzimage.cdek.ru\/images\/5477\/12572_image"}},{"@attributes":{"url":"https:\/\/pvzimage.cdek.ru\/images\/5477\/12574_image"}},{"@attributes":{"url":"https:\/\/pvzimage.cdek.ru\/images\/5477\/12576_image"}},{"@attributes":{"url":"https:\/\/pvzimage.cdek.ru\/images\/5477\/12578_image"}}],"WorkTimeY":[{"@attributes":{"day":"1","periods":"10:00\/20:00"}},{"@attributes":{"day":"2","periods":"10:00\/20:00"}},{"@attributes":{"day":"3","periods":"10:00\/20:00"}},{"@attributes":{"day":"4","periods":"10:00\/20:00"}},{"@attributes":{"day":"5","periods":"10:00\/20:00"}},{"@attributes":{"day":"6","periods":"10:00\/18:00"}},{"@attributes":{"day":"7","periods":"10:00\/18:00"}}],"WeightLimit":{"@attributes":{"WeightMin":"0","WeightMax":"35"}}}}