{"6405 Постамат ОМНИСДЭК":{"@attributes":{"Code":"GOL4","Status":"ACTIVE","PostalCode":"143040","Name":"6405 Постамат ОМНИСДЭК","CountryCode":"1","countryCodeIso":"RU","CountryName":"Россия","RegionCode":"9","RegionName":"Московская обл.","CityCode":"1102","City":"Голицыно","WorkTime":"Пн-Вс 09:00-19:00","Address":"ул. Советская, 52, корп. 6","FullAddress":"Россия, Московская обл., Голицыно, ул. Советская, 52, корп. 6","AddressComment":"Интернет","Phone":"+78007753553","Email":"","Note":"Интернет","coordX":"36.98329","coordY":"55.623076","Type":"POSTAMAT","ownerCode":"cdek","IsDressingRoom":"false","HaveCashless":"true","HaveCash":"false","AllowedCod":"true","TakeOnly":"false","IsHandout":"true","IsReception":"true","NearestStation":"Девятки","MetroStation":"","Site":"","Fulfillment":"false","FiasGuid":"963efb34-c804-43b4-9298-8e145d188ed0"},"PhoneDetail":{"@attributes":{"number":"+78007753553"}},"OfficeImage":[{"@attributes":{"url":"https:\/\/pvzimage.cdek.ru\/images\/7545\/24254_image"}},{"@attributes":{"url":"https:\/\/pvzimage.cdek.ru\/images\/7545\/24258_image"}},{"@attributes":{"url":"https:\/\/pvzimage.cdek.ru\/images\/7545\/24256_image"}}],"WorkTimeY":[{"@attributes":{"day":"1","periods":"09:00\/19:00"}},{"@attributes":{"day":"2","periods":"09:00\/19:00"}},{"@attributes":{"day":"3","periods":"09:00\/19:00"}},{"@attributes":{"day":"4","periods":"09:00\/19:00"}},{"@attributes":{"day":"5","periods":"09:00\/19:00"}},{"@attributes":{"day":"6","periods":"09:00\/19:00"}},{"@attributes":{"day":"7","periods":"09:00\/19:00"}}],"WeightLimit":{"@attributes":{"WeightMin":"0","WeightMax":"30"}},"Dimensions":{"@attributes":{"depth":"40.5","height":"36.5","width":"64.5"}}},"На Заводском, 13":{"@attributes":{"Code":"GOL1","Status":"ACTIVE","PostalCode":"143040","Name":"На Заводском, 13","CountryCode":"1","countryCodeIso":"RU","CountryName":"Россия","RegionCode":"9","RegionName":"Московская обл.","CityCode":"1102","City":"Голицыно","WorkTime":"Пн-Пт 10:00-19:00, Сб-Вс 10:00-19:00","Address":"пр-т. Заводской, 13","FullAddress":"Россия, Московская обл., Голицыно, пр-т. Заводской, 13","AddressComment":"со стороны Можайского шоссе : на круговом движении на станции первый съезд направо , далее прямо 250 метров, в сторону жк Князь Голицын. Слева второе красное трехэтажное здание, первый этаж.","Phone":"+79250666829","Email":"a.solonitsyna@cdek.ru","Note":"со стороны Можайского шоссе : на круговом движении на станции первый съезд направо , далее прямо 250 метров, в сторону жк Князь Голицын. Слева второе красное трехэтажное здание, первый этаж.","coordX":"36.982724","coordY":"55.6154","Type":"PVZ","ownerCode":"cdek","IsDressingRoom":"true","HaveCashless":"true","HaveCash":"true","AllowedCod":"true","TakeOnly":"false","IsHandout":"true","IsReception":"true","NearestStation":"Голицыно","MetroStation":"","Site":"","Fulfillment":"false","FiasGuid":"963efb34-c804-43b4-9298-8e145d188ed0"},"PhoneDetail":{"@attributes":{"number":"+79250666829"}},"OfficeImage":[{"@attributes":{"url":"https:\/\/pvzimage.cdek.ru\/images\/3120\/35132_image"}},{"@attributes":{"url":"https:\/\/pvzimage.cdek.ru\/images\/3120\/35134_image"}},{"@attributes":{"url":"https:\/\/pvzimage.cdek.ru\/images\/3120\/35136_image"}},{"@attributes":{"url":"https:\/\/pvzimage.cdek.ru\/images\/3120\/35140_image"}},{"@attributes":{"url":"https:\/\/pvzimage.cdek.ru\/images\/3120\/35142_image"}},{"@attributes":{"url":"https:\/\/pvzimage.cdek.ru\/images\/3120\/35144_image"}}],"WorkTimeY":[{"@attributes":{"day":"1","periods":"10:00\/19:00"}},{"@attributes":{"day":"2","periods":"10:00\/19:00"}},{"@attributes":{"day":"3","periods":"10:00\/19:00"}},{"@attributes":{"day":"4","periods":"10:00\/19:00"}},{"@attributes":{"day":"5","periods":"10:00\/19:00"}},{"@attributes":{"day":"6","periods":"10:00\/19:00"}},{"@attributes":{"day":"7","periods":"10:00\/19:00"}}]}}