{"На Таврической":{"@attributes":{"Code":"ALSH1","Status":"ACTIVE","PostalCode":"298510","Name":"На Таврической","CountryCode":"1","countryCodeIso":"RU","CountryName":"Россия","RegionCode":"90","RegionName":"Крым респ.","CityCode":"15502","City":"Алушта","WorkTime":"Пн-Пт 10:00-19:00, Сб 10:00-16:00","Address":"ул. Таврическая, 4а","FullAddress":"Россия, Крым респ., Алушта, ул. Таврическая, 4а","AddressComment":"","Phone":"+79780474737","Email":"v.shmatula@cdek.ru","Note":"","coordX":"34.4089432","coordY":"44.6801071","Type":"PVZ","ownerCode":"cdek","IsDressingRoom":"true","HaveCashless":"true","HaveCash":"true","AllowedCod":"true","TakeOnly":"false","IsHandout":"true","IsReception":"true","NearestStation":"ул. Таврическая","MetroStation":"","Site":"https:\/\/www.cdek.ru\/contacts\/g_alushta_ultavricheskaya_d_3.html","Fulfillment":"false","FiasGuid":"1fb30227-c758-4b1a-814b-eab9c8e7a582"},"PhoneDetail":{"@attributes":{"number":"+79780474737"}},"OfficeImage":[{"@attributes":{"url":"https:\/\/pvzimage.cdek.ru\/images\/312\/37582_image"}},{"@attributes":{"url":"https:\/\/pvzimage.cdek.ru\/images\/312\/37585_image"}},{"@attributes":{"url":"https:\/\/pvzimage.cdek.ru\/images\/312\/37586_image"}}],"WorkTimeY":[{"@attributes":{"day":"1","periods":"10:00\/19:00"}},{"@attributes":{"day":"2","periods":"10:00\/19:00"}},{"@attributes":{"day":"3","periods":"10:00\/19:00"}},{"@attributes":{"day":"4","periods":"10:00\/19:00"}},{"@attributes":{"day":"5","periods":"10:00\/19:00"}},{"@attributes":{"day":"6","periods":"10:00\/16:00"}}]},"На Автовокзале":{"@attributes":{"Code":"ALSH2","Status":"ACTIVE","PostalCode":"298500","Name":"На Автовокзале","CountryCode":"1","countryCodeIso":"RU","CountryName":"Россия","RegionCode":"90","RegionName":"Крым респ.","CityCode":"15502","City":"Алушта","WorkTime":"Пн-Пт 10:00-19:00, Сб 10:00-18:00, Вс 10:00-16:00","Address":"ул. Виноградная, 22","FullAddress":"Россия, Крым респ., Алушта, ул. Виноградная, 22","AddressComment":"От центрального автовокзала 300 метров  СДЭК находится между школой №3 и детским садом №8 \/ Бывший компьютерный магазин","Phone":"+79184256040","Email":"ev.prokopenko@cdek.ru","Note":"От центрального автовокзала 300 метров  СДЭК находится между школой №3 и детским садом №8 \/ Бывший компьютерный магазин","coordX":"34.395603","coordY":"44.673231","Type":"PVZ","ownerCode":"cdek","IsDressingRoom":"true","HaveCashless":"true","HaveCash":"true","AllowedCod":"true","TakeOnly":"false","IsHandout":"true","IsReception":"true","NearestStation":"Автовокзал","MetroStation":"","Site":"","Fulfillment":"false","FiasGuid":"1fb30227-c758-4b1a-814b-eab9c8e7a582"},"PhoneDetail":{"@attributes":{"number":"+79184256040"}},"OfficeImage":[{"@attributes":{"url":"https:\/\/pvzimage.cdek.ru\/images\/6175\/16849_image"}},{"@attributes":{"url":"https:\/\/pvzimage.cdek.ru\/images\/6175\/16851_image"}},{"@attributes":{"url":"https:\/\/pvzimage.cdek.ru\/images\/6175\/16853_image"}},{"@attributes":{"url":"https:\/\/pvzimage.cdek.ru\/images\/6175\/16855_image"}}],"WorkTimeY":[{"@attributes":{"day":"1","periods":"10:00\/19:00"}},{"@attributes":{"day":"2","periods":"10:00\/19:00"}},{"@attributes":{"day":"3","periods":"10:00\/19:00"}},{"@attributes":{"day":"4","periods":"10:00\/19:00"}},{"@attributes":{"day":"5","periods":"10:00\/19:00"}},{"@attributes":{"day":"6","periods":"10:00\/18:00"}},{"@attributes":{"day":"7","periods":"10:00\/16:00"}}]}}