{"На Вольского":{"@attributes":{"Code":"PPK4","Status":"ACTIVE","PostalCode":"683002","Name":"На Вольского","CountryCode":"1","countryCodeIso":"RU","CountryName":"Россия","RegionCode":"55","RegionName":"Камчатский край","CityCode":"285","City":"Петропавловск-Камчатский","WorkTime":"Пн-Пт 10:00-19:00, Сб 10:00-16:00","Address":"ул. Вольского, 8","FullAddress":"Россия, Камчатский край, Петропавловск-Камчатский, ул. Вольского, 8","AddressComment":"От Центрального Рынка Северовостока по направлению к ресторану Сванский двор, ТРЦ «КРЫМ»","Phone":"+74152344588","Email":"a.vorontsov@cdek.ru","Note":"От Центрального Рынка Северовостока по направлению к ресторану Сванский двор, ТРЦ «КРЫМ»","coordX":"158.644046","coordY":"53.070278","Type":"PVZ","ownerCode":"cdek","IsDressingRoom":"true","HaveCashless":"true","HaveCash":"true","AllowedCod":"true","TakeOnly":"false","IsHandout":"true","IsReception":"true","NearestStation":"Таранца","MetroStation":"","Site":"","Fulfillment":"false","FiasGuid":"0b3f0723-5fe0-4c23-af44-8082166c6d2e"},"PhoneDetail":{"@attributes":{"number":"+74152344588"}},"WorkTimeY":[{"@attributes":{"day":"1","periods":"10:00\/19:00"}},{"@attributes":{"day":"2","periods":"10:00\/19:00"}},{"@attributes":{"day":"3","periods":"10:00\/19:00"}},{"@attributes":{"day":"4","periods":"10:00\/19:00"}},{"@attributes":{"day":"5","periods":"10:00\/19:00"}},{"@attributes":{"day":"6","periods":"10:00\/16:00"}}]},"На Ленинградской":{"@attributes":{"Code":"PPK3","Status":"ACTIVE","PostalCode":"683003","Name":"На Ленинградской","CountryCode":"1","countryCodeIso":"RU","CountryName":"Россия","RegionCode":"55","RegionName":"Камчатский край","CityCode":"285","City":"Петропавловск-Камчатский","WorkTime":"Пн-Пт 09:00-19:00, Сб 10:00-16:00","Address":"ул. Ленинградская, 100","FullAddress":"Россия, Камчатский край, Петропавловск-Камчатский, ул. Ленинградская, 100","AddressComment":"","Phone":"+74152215216","Email":"e.bazhenova@cdek.ru","Note":"","coordX":"158.658532","coordY":"53.037782","Type":"PVZ","ownerCode":"cdek","IsDressingRoom":"true","HaveCashless":"true","HaveCash":"true","AllowedCod":"true","TakeOnly":"false","IsHandout":"true","IsReception":"true","NearestStation":"Комсомольская площадь","MetroStation":"","Site":"","Fulfillment":"false","FiasGuid":"0b3f0723-5fe0-4c23-af44-8082166c6d2e"},"PhoneDetail":{"@attributes":{"number":"+74152215216"}},"OfficeImage":[{"@attributes":{"url":"edu.api-pvz.imageRepository.service.cdek.tech:8008\/images\/2002\/1875_1_PPK3"}},{"@attributes":{"url":"edu.api-pvz.imageRepository.service.cdek.tech:8008\/images\/2002\/1877_3_PPK3"}},{"@attributes":{"url":"edu.api-pvz.imageRepository.service.cdek.tech:8008\/images\/2002\/1876_2_PPK3"}}],"WorkTimeY":[{"@attributes":{"day":"1","periods":"09:00\/19:00"}},{"@attributes":{"day":"2","periods":"09:00\/19:00"}},{"@attributes":{"day":"3","periods":"09:00\/19:00"}},{"@attributes":{"day":"4","periods":"09:00\/19:00"}},{"@attributes":{"day":"5","periods":"09:00\/19:00"}},{"@attributes":{"day":"6","periods":"10:00\/16:00"}}]},"На Бохняка":{"@attributes":{"Code":"PPK2","Status":"ACTIVE","PostalCode":"683031","Name":"На Бохняка","CountryCode":"1","countryCodeIso":"RU","CountryName":"Россия","RegionCode":"55","RegionName":"Камчатский край","CityCode":"285","City":"Петропавловск-Камчатский","WorkTime":"Пн-Пт 09:00-19:00, Сб 10:00-16:00","Address":"ул. Бохняка, 18","FullAddress":"Россия, Камчатский край, Петропавловск-Камчатский, ул. Бохняка, 18","AddressComment":"","Phone":"+74152307878","Note":"","coordX":"158.6207581","coordY":"53.0620193","Type":"PVZ","ownerCode":"cdek","IsDressingRoom":"true","HaveCashless":"true","HaveCash":"true","AllowedCod":"true","TakeOnly":"false","IsHandout":"true","IsReception":"true","NearestStation":"","MetroStation":"","Site":"https:\/\/www.cdek.ru\/contacts\/g_petropavlovsk-kamchatskiy_ul_bohnyaka_d_18.html","Fulfillment":"false","FiasGuid":"0b3f0723-5fe0-4c23-af44-8082166c6d2e"},"PhoneDetail":{"@attributes":{"number":"+74152307878"}},"WorkTimeY":[{"@attributes":{"day":"1","periods":"09:00\/19:00"}},{"@attributes":{"day":"2","periods":"09:00\/19:00"}},{"@attributes":{"day":"3","periods":"09:00\/19:00"}},{"@attributes":{"day":"4","periods":"09:00\/19:00"}},{"@attributes":{"day":"5","periods":"09:00\/19:00"}},{"@attributes":{"day":"6","periods":"10:00\/16:00"}}]},"Остановка 10 км.":{"@attributes":{"Code":"PPK6","Status":"ACTIVE","PostalCode":"683023","Name":"Остановка 10 км.","CountryCode":"1","countryCodeIso":"RU","CountryName":"Россия","RegionCode":"55","RegionName":"Камчатский край","CityCode":"285","City":"Петропавловск-Камчатский","WorkTime":"Пн-Пт 09:00-19:00, Сб 10:00-16:00","Address":"ул. Победы, 65а","FullAddress":"Россия, Камчатский край, Петропавловск-Камчатский, ул. Победы, 65а","AddressComment":"За остановкой «10 км», слева от здания «Моховской»","Phone":"+74152405251","Email":"a.sayko@cdek.ru","Note":"За остановкой «10 км», слева от здания «Моховской»","coordX":"158.590997","coordY":"53.070844","Type":"PVZ","ownerCode":"cdek","IsDressingRoom":"true","HaveCashless":"true","HaveCash":"true","AllowedCod":"true","TakeOnly":"false","IsHandout":"true","IsReception":"true","NearestStation":"10 км","MetroStation":"","Site":"","Fulfillment":"false","FiasGuid":"0b3f0723-5fe0-4c23-af44-8082166c6d2e"},"PhoneDetail":{"@attributes":{"number":"+74152405251"}},"OfficeImage":[{"@attributes":{"url":"edu.api-pvz.imageRepository.service.cdek.tech:8008\/images\/2812\/3321_3_PPK6"}},{"@attributes":{"url":"edu.api-pvz.imageRepository.service.cdek.tech:8008\/images\/2812\/3320_2_PPK6"}},{"@attributes":{"url":"edu.api-pvz.imageRepository.service.cdek.tech:8008\/images\/2812\/3319_1_PPK6"}},{"@attributes":{"url":"edu.api-pvz.imageRepository.service.cdek.tech:8008\/images\/2812\/3322_4_PPK6"}}],"WorkTimeY":[{"@attributes":{"day":"1","periods":"09:00\/19:00"}},{"@attributes":{"day":"2","periods":"09:00\/19:00"}},{"@attributes":{"day":"3","periods":"09:00\/19:00"}},{"@attributes":{"day":"4","periods":"09:00\/19:00"}},{"@attributes":{"day":"5","periods":"09:00\/19:00"}},{"@attributes":{"day":"6","periods":"10:00\/16:00"}}]}}