{"На Карла Маркса":{"@attributes":{"Code":"AGR1","Status":"ACTIVE","PostalCode":"422230","Name":"На Карла Маркса","CountryCode":"1","countryCodeIso":"RU","CountryName":"Россия","RegionCode":"39","RegionName":"Татарстан респ.","CityCode":"1497","City":"Агрыз","WorkTime":"Пн-Вс 08:00-20:00","Address":"ул. Карла Маркса, 16","FullAddress":"Россия, Татарстан респ., Агрыз, ул. Карла Маркса, 16","AddressComment":"По центральной улице возле Сбербанка","Phone":"+79655888899","Email":"agryz@cdek.ru","Note":"По центральной улице возле Сбербанка","coordX":"52.994862","coordY":"56.525797","Type":"PVZ","ownerCode":"cdek","IsDressingRoom":"true","HaveCashless":"true","HaveCash":"true","AllowedCod":"true","TakeOnly":"false","IsHandout":"true","IsReception":"true","NearestStation":"ул. Карла Маркса","MetroStation":"","Site":"","Fulfillment":"false","FiasGuid":"9f936889-a757-419e-890a-d4cc1fa95e93"},"PhoneDetail":{"@attributes":{"number":"+79655888899"}},"OfficeImage":[{"@attributes":{"url":"https:\/\/pvzimage.cdek.ru\/images\/6736\/17813_image"}},{"@attributes":{"url":"https:\/\/pvzimage.cdek.ru\/images\/6736\/17811_image"}},{"@attributes":{"url":"https:\/\/pvzimage.cdek.ru\/images\/6736\/17815_image"}},{"@attributes":{"url":"https:\/\/pvzimage.cdek.ru\/images\/6736\/17817_image"}}],"WorkTimeY":[{"@attributes":{"day":"1","periods":"08:00\/20:00"}},{"@attributes":{"day":"2","periods":"08:00\/20:00"}},{"@attributes":{"day":"3","periods":"08:00\/20:00"}},{"@attributes":{"day":"4","periods":"08:00\/20:00"}},{"@attributes":{"day":"5","periods":"08:00\/20:00"}},{"@attributes":{"day":"6","periods":"08:00\/20:00"}},{"@attributes":{"day":"7","periods":"08:00\/20:00"}}]}}