{"На 79 Гвардейской Дивизии":{"@attributes":{"Code":"TOM13","Status":"ACTIVE","PostalCode":"634057","Name":"На 79 Гвардейской Дивизии","CountryCode":"1","countryCodeIso":"RU","CountryName":"Россия","RegionCode":"53","RegionName":"Томская обл.","CityCode":"269","City":"Томск","WorkTime":"Пн-Пт 10:00-20:00, Сб-Вс 10:00-18:00","Address":"ул. 79 Гвардейской Дивизии, 6","FullAddress":"Россия, Томская обл., Томск, ул. 79 Гвардейской Дивизии, 6","AddressComment":"отдельный вход, левый торец здания, рядом с магазином «4 Угла»","Phone":"+79588550797, +79588550797","Email":"v.shapran@cdek.ru","Note":"отдельный вход, левый торец здания, рядом с магазином «4 Угла»","coordX":"84.982481","coordY":"56.506778","Type":"PVZ","ownerCode":"cdek","IsDressingRoom":"true","HaveCashless":"true","HaveCash":"true","AllowedCod":"true","TakeOnly":"false","IsHandout":"true","IsReception":"true","NearestStation":"«Говорова»","MetroStation":"","Site":"","Fulfillment":"false","FiasGuid":"e3b0eae8-a4ce-4779-ae04-5c0797de66be"},"PhoneDetail":[{"@attributes":{"number":"+79588550797"}},{"@attributes":{"number":"+79588550797"}}],"OfficeImage":[{"@attributes":{"url":"https:\/\/pvzimage.cdek.ru\/images\/2050\/1908_1_TOM13"}},{"@attributes":{"url":"https:\/\/pvzimage.cdek.ru\/images\/2050\/33520_image"}},{"@attributes":{"url":"https:\/\/pvzimage.cdek.ru\/images\/2050\/33524_image"}},{"@attributes":{"url":"https:\/\/pvzimage.cdek.ru\/images\/2050\/33522_image"}}],"WorkTimeY":[{"@attributes":{"day":"1","periods":"10:00\/20:00"}},{"@attributes":{"day":"2","periods":"10:00\/20:00"}},{"@attributes":{"day":"3","periods":"10:00\/20:00"}},{"@attributes":{"day":"4","periods":"10:00\/20:00"}},{"@attributes":{"day":"5","periods":"10:00\/20:00"}},{"@attributes":{"day":"6","periods":"10:00\/18:00"}},{"@attributes":{"day":"7","periods":"10:00\/18:00"}}]},"На Мира 21":{"@attributes":{"Code":"TOM42","Status":"ACTIVE","PostalCode":"634057","Name":"На Мира 21","CountryCode":"1","countryCodeIso":"RU","CountryName":"Россия","RegionCode":"53","RegionName":"Томская обл.","CityCode":"269","City":"Томск","WorkTime":"Пн-Пт 09:00-21:00, Сб-Вс 10:00-18:00","Address":"пр-т Мира, 21","FullAddress":"Россия, Томская обл., Томск, пр-т Мира, 21","AddressComment":"Офис расположен на основной магистрали района \"Каштак\". В 150 метрах от остановки общественного транспорта \"Поликлиника №10\" в сторону улицы Интернационалистов. Находится на 1-ом этаже в помещении магазина Мария-Ра.","Phone":"+79009231100","Email":"k.suhanov@cdek.ru","Note":"Офис расположен на основной магистрали района \"Каштак\". В 150 метрах от остановки общественного транспорта \"Поликлиника №10\" в сторону улицы Интернационалистов. Находится на 1-ом этаже в помещении магазина Мария-Ра.","coordX":"84.97835","coordY":"56.51555","Type":"PVZ","ownerCode":"cdek","IsDressingRoom":"true","HaveCashless":"true","HaveCash":"true","AllowedCod":"true","TakeOnly":"false","IsHandout":"true","IsReception":"true","NearestStation":"Поликлиника №10, Автопарк (Проспект Мира)","MetroStation":"","Site":"","Fulfillment":"false","FiasGuid":"e3b0eae8-a4ce-4779-ae04-5c0797de66be"},"PhoneDetail":{"@attributes":{"number":"+79009231100"}},"OfficeImage":[{"@attributes":{"url":"https:\/\/pvzimage.cdek.ru\/images\/9330\/46508_image"}},{"@attributes":{"url":"https:\/\/pvzimage.cdek.ru\/images\/9330\/46510_image"}},{"@attributes":{"url":"https:\/\/pvzimage.cdek.ru\/images\/9330\/46512_image"}},{"@attributes":{"url":"https:\/\/pvzimage.cdek.ru\/images\/9330\/46514_image"}},{"@attributes":{"url":"https:\/\/pvzimage.cdek.ru\/images\/9330\/46516_image"}},{"@attributes":{"url":"https:\/\/pvzimage.cdek.ru\/images\/9330\/46696_image"}}],"WorkTimeY":[{"@attributes":{"day":"1","periods":"09:00\/21:00"}},{"@attributes":{"day":"2","periods":"09:00\/21:00"}},{"@attributes":{"day":"3","periods":"09:00\/21:00"}},{"@attributes":{"day":"4","periods":"09:00\/21:00"}},{"@attributes":{"day":"5","periods":"09:00\/21:00"}},{"@attributes":{"day":"6","periods":"10:00\/18:00"}},{"@attributes":{"day":"7","periods":"10:00\/18:00"}}]},"7292 Постамат ОМНИСДЭК":{"@attributes":{"Code":"TOM37","Status":"ACTIVE","PostalCode":"634057","Name":"7292 Постамат ОМНИСДЭК","CountryCode":"1","countryCodeIso":"RU","CountryName":"Россия","RegionCode":"53","RegionName":"Томская обл.","CityCode":"269","City":"Томск","WorkTime":"Пн-Вс 08:00-22:00","Address":"проспект Мира, 27А","FullAddress":"Россия, Томская обл., Томск, проспект Мира, 27А","AddressComment":"Мария-Ра","Phone":"+78007753553","Email":"","Note":"Мария-Ра","coordX":"84.98032","coordY":"56.517256","Type":"POSTAMAT","ownerCode":"cdek","IsDressingRoom":"false","HaveCashless":"true","HaveCash":"false","AllowedCod":"true","TakeOnly":"false","IsHandout":"true","IsReception":"true","NearestStation":"Автопарк","MetroStation":"","Site":"","Fulfillment":"false","FiasGuid":"e3b0eae8-a4ce-4779-ae04-5c0797de66be"},"PhoneDetail":{"@attributes":{"number":"+78007753553"}},"OfficeImage":[{"@attributes":{"url":"https:\/\/pvzimage.cdek.ru\/images\/8693\/40790_image"}},{"@attributes":{"url":"https:\/\/pvzimage.cdek.ru\/images\/8693\/40792_image"}}],"WorkTimeY":[{"@attributes":{"day":"1","periods":"08:00\/22:00"}},{"@attributes":{"day":"2","periods":"08:00\/22:00"}},{"@attributes":{"day":"3","periods":"08:00\/22:00"}},{"@attributes":{"day":"4","periods":"08:00\/22:00"}},{"@attributes":{"day":"5","periods":"08:00\/22:00"}},{"@attributes":{"day":"6","periods":"08:00\/22:00"}},{"@attributes":{"day":"7","periods":"08:00\/22:00"}}],"WeightLimit":{"@attributes":{"WeightMin":"0","WeightMax":"30"}},"Dimensions":{"@attributes":{"depth":"40.5","height":"36.5","width":"64.5"}}},"7279 Постамат ОМНИСДЭК":{"@attributes":{"Code":"TOM38","Status":"ACTIVE","PostalCode":"634031","Name":"7279 Постамат ОМНИСДЭК","CountryCode":"1","countryCodeIso":"RU","CountryName":"Россия","RegionCode":"53","RegionName":"Томская обл.","CityCode":"269","City":"Томск","WorkTime":"Пн-Вс 08:00-22:00","Address":"ул. Ивановского, 20","FullAddress":"Россия, Томская обл., Томск, ул. Ивановского, 20","AddressComment":"Мария-Ра","Phone":"+78007753553","Email":"","Note":"Мария-Ра","coordX":"85.076108","coordY":"56.502733","Type":"POSTAMAT","ownerCode":"cdek","IsDressingRoom":"false","HaveCashless":"true","HaveCash":"false","AllowedCod":"true","TakeOnly":"false","IsHandout":"true","IsReception":"true","NearestStation":"ул. Ивановского, 20","MetroStation":"","Site":"","Fulfillment":"false","FiasGuid":"e3b0eae8-a4ce-4779-ae04-5c0797de66be"},"PhoneDetail":{"@attributes":{"number":"+78007753553"}},"OfficeImage":[{"@attributes":{"url":"https:\/\/pvzimage.cdek.ru\/images\/8725\/42548_image"}},{"@attributes":{"url":"https:\/\/pvzimage.cdek.ru\/images\/8725\/42550_image"}}],"WorkTimeY":[{"@attributes":{"day":"1","periods":"08:00\/22:00"}},{"@attributes":{"day":"2","periods":"08:00\/22:00"}},{"@attributes":{"day":"3","periods":"08:00\/22:00"}},{"@attributes":{"day":"4","periods":"08:00\/22:00"}},{"@attributes":{"day":"5","periods":"08:00\/22:00"}},{"@attributes":{"day":"6","periods":"08:00\/22:00"}},{"@attributes":{"day":"7","periods":"08:00\/22:00"}}],"WeightLimit":{"@attributes":{"WeightMin":"0","WeightMax":"30"}},"Dimensions":{"@attributes":{"depth":"40.5","height":"36.5","width":"64.5"}}},"На 1-ой Рабочей":{"@attributes":{"Code":"TOM4","Status":"ACTIVE","PostalCode":"634049","Name":"На 1-ой Рабочей","CountryCode":"1","countryCodeIso":"RU","CountryName":"Россия","RegionCode":"53","RegionName":"Томская обл.","CityCode":"269","City":"Томск","WorkTime":"Пн-Пт 10:00-20:00, Сб-Вс 10:00-18:00","Address":"ул. 1-я Рабочая, 8","FullAddress":"Россия, Томская обл., Томск, ул. 1-я Рабочая, 8","AddressComment":"","Phone":"+73822609080","Email":"s.kazakov@cdek.ru","Note":"","coordX":"85.006137","coordY":"56.505395","Type":"PVZ","ownerCode":"cdek","IsDressingRoom":"true","HaveCashless":"true","HaveCash":"true","AllowedCod":"true","TakeOnly":"false","IsHandout":"true","IsReception":"true","NearestStation":"1-я Рабочая","MetroStation":"","Site":"https:\/\/www.cdek.ru\/contacts\/g_tomsk_ul_1-aya_rabochaya_d8.html","Fulfillment":"false","FiasGuid":"e3b0eae8-a4ce-4779-ae04-5c0797de66be"},"PhoneDetail":{"@attributes":{"number":"+73822609080"}},"OfficeImage":[{"@attributes":{"url":"https:\/\/pvzimage.cdek.ru\/images\/1184\/33544_image"}},{"@attributes":{"url":"https:\/\/pvzimage.cdek.ru\/images\/1184\/33554_image"}},{"@attributes":{"url":"https:\/\/pvzimage.cdek.ru\/images\/1184\/33548_image"}},{"@attributes":{"url":"https:\/\/pvzimage.cdek.ru\/images\/1184\/33552_image"}},{"@attributes":{"url":"https:\/\/pvzimage.cdek.ru\/images\/1184\/33550_image"}}],"WorkTimeY":[{"@attributes":{"day":"1","periods":"10:00\/20:00"}},{"@attributes":{"day":"2","periods":"10:00\/20:00"}},{"@attributes":{"day":"3","periods":"10:00\/20:00"}},{"@attributes":{"day":"4","periods":"10:00\/20:00"}},{"@attributes":{"day":"5","periods":"10:00\/20:00"}},{"@attributes":{"day":"6","periods":"10:00\/18:00"}},{"@attributes":{"day":"7","periods":"10:00\/18:00"}}]},"Косарева":{"@attributes":{"Code":"TOM23","Status":"ACTIVE","PostalCode":"634012","Name":"Косарева","CountryCode":"1","countryCodeIso":"RU","CountryName":"Россия","RegionCode":"53","RegionName":"Томская обл.","CityCode":"269","City":"Томск","WorkTime":"Пн-Пт 10:00-20:00, Сб-Вс 10:00-18:00","Address":"пр-т. Кирова, 59","FullAddress":"Россия, Томская обл., Томск, пр-т. Кирова, 59","AddressComment":"Остановка \"ул. Косарева\" в сторону Томска-1, сразу за остановкой дом, офис во дворе дома около первого подъезда.","Phone":"+79138475793","Email":"av.borlukov@cdek.ru","Note":"Остановка \"ул. Косарева\" в сторону Томска-1, сразу за остановкой дом, офис во дворе дома около первого подъезда.","coordX":"84.985621","coordY":"56.463113","Type":"PVZ","ownerCode":"cdek","IsDressingRoom":"true","HaveCashless":"true","HaveCash":"true","AllowedCod":"true","TakeOnly":"false","IsHandout":"true","IsReception":"true","NearestStation":"ул. Косарева","MetroStation":"","Site":"","Fulfillment":"false","FiasGuid":"e3b0eae8-a4ce-4779-ae04-5c0797de66be"},"PhoneDetail":{"@attributes":{"number":"+79138475793"}},"OfficeImage":[{"@attributes":{"url":"https:\/\/pvzimage.cdek.ru\/images\/7040\/19264_image"}},{"@attributes":{"url":"https:\/\/pvzimage.cdek.ru\/images\/7040\/19270_image"}},{"@attributes":{"url":"https:\/\/pvzimage.cdek.ru\/images\/7040\/19266_image"}},{"@attributes":{"url":"https:\/\/pvzimage.cdek.ru\/images\/7040\/19268_image"}}],"WorkTimeY":[{"@attributes":{"day":"1","periods":"10:00\/20:00"}},{"@attributes":{"day":"2","periods":"10:00\/20:00"}},{"@attributes":{"day":"3","periods":"10:00\/20:00"}},{"@attributes":{"day":"4","periods":"10:00\/20:00"}},{"@attributes":{"day":"5","periods":"10:00\/20:00"}},{"@attributes":{"day":"6","periods":"10:00\/18:00"}},{"@attributes":{"day":"7","periods":"10:00\/18:00"}}]},"Центральный рынок":{"@attributes":{"Code":"TOM18","Status":"ACTIVE","PostalCode":"634009","Name":"Центральный рынок","CountryCode":"1","countryCodeIso":"RU","CountryName":"Россия","RegionCode":"53","RegionName":"Томская обл.","CityCode":"269","City":"Томск","WorkTime":"Пн-Пт 10:00-20:00, Сб-Вс 10:00-18:00","Address":"пр. Ленина,, 159","FullAddress":"Россия, Томская обл., Томск, пр. Ленина,, 159","AddressComment":"ТЦ «Проспект», 1 этаж 2 крыльцо","Phone":"+79521794022","Email":"am.tatarkina@cdek.ru","Note":"ТЦ «Проспект», 1 этаж 2 крыльцо","coordX":"84.948834","coordY":"56.497889","Type":"PVZ","ownerCode":"cdek","IsDressingRoom":"true","HaveCashless":"true","HaveCash":"true","AllowedCod":"true","TakeOnly":"false","IsHandout":"true","IsReception":"true","NearestStation":"Центральный рынок","MetroStation":"","Site":"","Fulfillment":"false","FiasGuid":"e3b0eae8-a4ce-4779-ae04-5c0797de66be"},"PhoneDetail":{"@attributes":{"number":"+79521794022"}},"OfficeImage":[{"@attributes":{"url":"https:\/\/pvzimage.cdek.ru\/images\/4164\/5991_image"}},{"@attributes":{"url":"https:\/\/pvzimage.cdek.ru\/images\/4164\/5993_image"}},{"@attributes":{"url":"https:\/\/pvzimage.cdek.ru\/images\/4164\/5995_image"}},{"@attributes":{"url":"https:\/\/pvzimage.cdek.ru\/images\/4164\/5999_image"}},{"@attributes":{"url":"https:\/\/pvzimage.cdek.ru\/images\/4164\/6001_image"}},{"@attributes":{"url":"https:\/\/pvzimage.cdek.ru\/images\/4164\/6003_image"}}],"WorkTimeY":[{"@attributes":{"day":"1","periods":"10:00\/20:00"}},{"@attributes":{"day":"2","periods":"10:00\/20:00"}},{"@attributes":{"day":"3","periods":"10:00\/20:00"}},{"@attributes":{"day":"4","periods":"10:00\/20:00"}},{"@attributes":{"day":"5","periods":"10:00\/20:00"}},{"@attributes":{"day":"6","periods":"10:00\/18:00"}},{"@attributes":{"day":"7","periods":"10:00\/18:00"}}]},"7148 Постамат ОМНИСДЭК":{"@attributes":{"Code":"TOM25","Status":"ACTIVE","PostalCode":"634045","Name":"7148 Постамат ОМНИСДЭК","CountryCode":"1","countryCodeIso":"RU","CountryName":"Россия","RegionCode":"53","RegionName":"Томская обл.","CityCode":"269","City":"Томск","WorkTime":"Пн-Вс 09:00-21:00","Address":"ул. Нахимова, 15а","FullAddress":"Россия, Томская обл., Томск, ул. Нахимова, 15а","AddressComment":"Офис компании \"Деньги сразу\"","Phone":"+78007753553","Email":"","Note":"Офис компании \"Деньги сразу\"","coordX":"84.973215","coordY":"56.455001","Type":"POSTAMAT","ownerCode":"cdek","IsDressingRoom":"false","HaveCashless":"true","HaveCash":"false","AllowedCod":"true","TakeOnly":"false","IsHandout":"true","IsReception":"true","NearestStation":"Детский мир","MetroStation":"","Site":"","Fulfillment":"false","FiasGuid":"e3b0eae8-a4ce-4779-ae04-5c0797de66be"},"PhoneDetail":{"@attributes":{"number":"+78007753553"}},"OfficeImage":[{"@attributes":{"url":"https:\/\/pvzimage.cdek.ru\/images\/7628\/25454_image"}},{"@attributes":{"url":"https:\/\/pvzimage.cdek.ru\/images\/7628\/25456_image"}}],"WorkTimeY":[{"@attributes":{"day":"1","periods":"09:00\/21:00"}},{"@attributes":{"day":"2","periods":"09:00\/21:00"}},{"@attributes":{"day":"3","periods":"09:00\/21:00"}},{"@attributes":{"day":"4","periods":"09:00\/21:00"}},{"@attributes":{"day":"5","periods":"09:00\/21:00"}},{"@attributes":{"day":"6","periods":"09:00\/21:00"}},{"@attributes":{"day":"7","periods":"09:00\/21:00"}}],"WeightLimit":{"@attributes":{"WeightMin":"0","WeightMax":"30"}},"Dimensions":{"@attributes":{"depth":"40.5","height":"36.5","width":"64.5"}}},"На Пушкина":{"@attributes":{"Code":"TOM16","Status":"ACTIVE","PostalCode":"634003","Name":"На Пушкина","CountryCode":"1","countryCodeIso":"RU","CountryName":"Россия","RegionCode":"53","RegionName":"Томская обл.","CityCode":"269","City":"Томск","WorkTime":"Пн-Пт 09:00-20:00, Сб-Вс 10:00-18:00","Address":"ул. Пушкина, 32, 101","FullAddress":"Россия, Томская обл., Томск, ул. Пушкина, 32, 101","AddressComment":"Автобусом до остановки «Дом Радио», автомобилем – ориентир «Белое Озеро»","Phone":"+79914483939","Email":"i.abdykadyrov@cdek.ru","Note":"Автобусом до остановки «Дом Радио», автомобилем – ориентир «Белое Озеро»","coordX":"84.963288","coordY":"56.497213","Type":"PVZ","ownerCode":"cdek","IsDressingRoom":"true","HaveCashless":"true","HaveCash":"true","AllowedCod":"true","TakeOnly":"false","IsHandout":"true","IsReception":"true","NearestStation":"Дом Радио","MetroStation":"","Site":"","Fulfillment":"false","FiasGuid":"e3b0eae8-a4ce-4779-ae04-5c0797de66be"},"PhoneDetail":{"@attributes":{"number":"+79914483939"}},"OfficeImage":[{"@attributes":{"url":"https:\/\/pvzimage.cdek.ru\/images\/3493\/4183_image"}},{"@attributes":{"url":"https:\/\/pvzimage.cdek.ru\/images\/3493\/4185_image"}},{"@attributes":{"url":"https:\/\/pvzimage.cdek.ru\/images\/3493\/4187_image"}}],"WorkTimeY":[{"@attributes":{"day":"1","periods":"09:00\/20:00"}},{"@attributes":{"day":"2","periods":"09:00\/20:00"}},{"@attributes":{"day":"3","periods":"09:00\/20:00"}},{"@attributes":{"day":"4","periods":"09:00\/20:00"}},{"@attributes":{"day":"5","periods":"09:00\/20:00"}},{"@attributes":{"day":"6","periods":"10:00\/18:00"}},{"@attributes":{"day":"7","periods":"10:00\/18:00"}}],"WeightLimit":{"@attributes":{"WeightMin":"0","WeightMax":"40"}}},"На Южной":{"@attributes":{"Code":"TOM21","Status":"ACTIVE","PostalCode":"634045","Name":"На Южной","CountryCode":"1","countryCodeIso":"RU","CountryName":"Россия","RegionCode":"53","RegionName":"Томская обл.","CityCode":"269","City":"Томск","WorkTime":"Пн-Пт 10:00-20:00, Сб-Вс 10:00-18:00","Address":"ул. 19 Гвардейской Дивизии, 7","FullAddress":"Россия, Томская обл., Томск, ул. 19 Гвардейской Дивизии, 7","AddressComment":"за остановкой \"ПЛОЩАДЬ ЮЖНАЯ\" в сторону Буревестника","Phone":"+73822256957","Email":"tomsk-1@cdek.ru","Note":"за остановкой \"ПЛОЩАДЬ ЮЖНАЯ\" в сторону Буревестника","coordX":"84.977491","coordY":"56.451896","Type":"PVZ","ownerCode":"cdek","IsDressingRoom":"true","HaveCashless":"true","HaveCash":"true","AllowedCod":"true","TakeOnly":"false","IsHandout":"true","IsReception":"true","NearestStation":"Площадь Южная","MetroStation":"","Site":"","Fulfillment":"false","FiasGuid":"e3b0eae8-a4ce-4779-ae04-5c0797de66be"},"PhoneDetail":{"@attributes":{"number":"+73822256957"}},"OfficeImage":[{"@attributes":{"url":"https:\/\/pvzimage.cdek.ru\/images\/5471\/13937_image"}},{"@attributes":{"url":"https:\/\/pvzimage.cdek.ru\/images\/5471\/13939_image"}},{"@attributes":{"url":"https:\/\/pvzimage.cdek.ru\/images\/5471\/44282_image"}}],"WorkTimeY":[{"@attributes":{"day":"1","periods":"10:00\/20:00"}},{"@attributes":{"day":"2","periods":"10:00\/20:00"}},{"@attributes":{"day":"3","periods":"10:00\/20:00"}},{"@attributes":{"day":"4","periods":"10:00\/20:00"}},{"@attributes":{"day":"5","periods":"10:00\/20:00"}},{"@attributes":{"day":"6","periods":"10:00\/18:00"}},{"@attributes":{"day":"7","periods":"10:00\/18:00"}}],"WeightLimit":{"@attributes":{"WeightMin":"0","WeightMax":"35"}}},"6516 Постамат ОМНИСДЭК":{"@attributes":{"Code":"TOM30","Status":"ACTIVE","PostalCode":"634034","Name":"6516 Постамат ОМНИСДЭК","CountryCode":"1","countryCodeIso":"RU","CountryName":"Россия","RegionCode":"53","RegionName":"Томская обл.","CityCode":"269","City":"Томск","WorkTime":"Пн-Вс 08:00-21:00","Address":"ул. Нахимова, 8, стр. 37","FullAddress":"Россия, Томская обл., Томск, ул. Нахимова, 8, стр. 37","AddressComment":"ПВЗ СДЭК","Phone":"+78007753553","Email":"","Note":"ПВЗ СДЭК","coordX":"84.957144","coordY":"56.458144","Type":"POSTAMAT","ownerCode":"cdek","IsDressingRoom":"false","HaveCashless":"true","HaveCash":"false","AllowedCod":"true","TakeOnly":"false","IsHandout":"true","IsReception":"true","NearestStation":"ул. Белинского","MetroStation":"","Site":"","Fulfillment":"false","FiasGuid":"e3b0eae8-a4ce-4779-ae04-5c0797de66be"},"PhoneDetail":{"@attributes":{"number":"+78007753553"}},"OfficeImage":[{"@attributes":{"url":"https:\/\/pvzimage.cdek.ru\/images\/8159\/33690_image"}},{"@attributes":{"url":"https:\/\/pvzimage.cdek.ru\/images\/8159\/33694_image"}}],"WorkTimeY":[{"@attributes":{"day":"1","periods":"08:00\/21:00"}},{"@attributes":{"day":"2","periods":"08:00\/21:00"}},{"@attributes":{"day":"3","periods":"08:00\/21:00"}},{"@attributes":{"day":"4","periods":"08:00\/21:00"}},{"@attributes":{"day":"5","periods":"08:00\/21:00"}},{"@attributes":{"day":"6","periods":"08:00\/21:00"}},{"@attributes":{"day":"7","periods":"08:00\/21:00"}}],"WeightLimit":{"@attributes":{"WeightMin":"0","WeightMax":"30"}},"Dimensions":{"@attributes":{"depth":"40.5","height":"36.5","width":"64.5"}}},"На Ленской 31":{"@attributes":{"Code":"TOM29","Status":"ACTIVE","PostalCode":"634026","Name":"На Ленской 31","CountryCode":"1","countryCodeIso":"RU","CountryName":"Россия","RegionCode":"53","RegionName":"Томская обл.","CityCode":"269","City":"Томск","WorkTime":"Пн-Пт 10:00-20:00, Сб-Вс 10:00-18:00","Address":"ул.Ленская, 31","FullAddress":"Россия, Томская обл., Томск, ул.Ленская, 31","AddressComment":"Остановка пер.Светлый, спуститься вниз, будет видно 17-ти этажное здание, последний подъезд, первый этаж","Phone":"+79234323942","Email":"n.valitova@cdek.ru","Note":"Остановка пер.Светлый, спуститься вниз, будет видно 17-ти этажное здание, последний подъезд, первый этаж","coordX":"84.973466","coordY":"56.521989","Type":"PVZ","ownerCode":"cdek","IsDressingRoom":"true","HaveCashless":"true","HaveCash":"true","AllowedCod":"true","TakeOnly":"false","IsHandout":"true","IsReception":"true","NearestStation":"пер. Светлый","MetroStation":"","Site":"","Fulfillment":"false","FiasGuid":"e3b0eae8-a4ce-4779-ae04-5c0797de66be"},"PhoneDetail":{"@attributes":{"number":"+79234323942"}},"OfficeImage":[{"@attributes":{"url":"https:\/\/pvzimage.cdek.ru\/images\/7889\/44922_image"}},{"@attributes":{"url":"https:\/\/pvzimage.cdek.ru\/images\/7889\/44924_image"}},{"@attributes":{"url":"https:\/\/pvzimage.cdek.ru\/images\/7889\/44926_image"}},{"@attributes":{"url":"https:\/\/pvzimage.cdek.ru\/images\/7889\/44928_image"}}],"WorkTimeY":[{"@attributes":{"day":"1","periods":"10:00\/20:00"}},{"@attributes":{"day":"2","periods":"10:00\/20:00"}},{"@attributes":{"day":"3","periods":"10:00\/20:00"}},{"@attributes":{"day":"4","periods":"10:00\/20:00"}},{"@attributes":{"day":"5","periods":"10:00\/20:00"}},{"@attributes":{"day":"6","periods":"10:00\/18:00"}},{"@attributes":{"day":"7","periods":"10:00\/18:00"}}]},"На Нарановича":{"@attributes":{"Code":"TOM17","Status":"ACTIVE","PostalCode":"634030","Name":"На Нарановича","CountryCode":"1","countryCodeIso":"RU","CountryName":"Россия","RegionCode":"53","RegionName":"Томская обл.","CityCode":"269","City":"Томск","WorkTime":"Пн-Пт 10:00-20:00, Сб-Вс 10:00-18:00","Address":"ул. Павла Нарановича, 10","FullAddress":"Россия, Томская обл., Томск, ул. Павла Нарановича, 10","AddressComment":"Ближайшие остановки «Бассенй» и «Зеленые горки», отдельный вход напротив детского сада №83","Phone":"+73822609081","Email":"lv.kazakova@cdek.ru","Note":"Ближайшие остановки «Бассенй» и «Зеленые горки», отдельный вход напротив детского сада №83","coordX":"85.054845","coordY":"56.492746","Type":"PVZ","ownerCode":"cdek","IsDressingRoom":"true","HaveCashless":"true","HaveCash":"true","AllowedCod":"true","TakeOnly":"false","IsHandout":"true","IsReception":"true","NearestStation":"«Бассейн» и «Зеленые горки»","MetroStation":"","Site":"","Fulfillment":"false","FiasGuid":"e3b0eae8-a4ce-4779-ae04-5c0797de66be"},"PhoneDetail":{"@attributes":{"number":"+73822609081"}},"OfficeImage":[{"@attributes":{"url":"https:\/\/pvzimage.cdek.ru\/images\/4134\/33480_image"}},{"@attributes":{"url":"https:\/\/pvzimage.cdek.ru\/images\/4134\/33482_image"}},{"@attributes":{"url":"https:\/\/pvzimage.cdek.ru\/images\/4134\/33484_image"}},{"@attributes":{"url":"https:\/\/pvzimage.cdek.ru\/images\/4134\/33487_image"}},{"@attributes":{"url":"https:\/\/pvzimage.cdek.ru\/images\/4134\/33488_image"}},{"@attributes":{"url":"https:\/\/pvzimage.cdek.ru\/images\/4134\/33490_image"}}],"WorkTimeY":[{"@attributes":{"day":"1","periods":"10:00\/20:00"}},{"@attributes":{"day":"2","periods":"10:00\/20:00"}},{"@attributes":{"day":"3","periods":"10:00\/20:00"}},{"@attributes":{"day":"4","periods":"10:00\/20:00"}},{"@attributes":{"day":"5","periods":"10:00\/20:00"}},{"@attributes":{"day":"6","periods":"10:00\/18:00"}},{"@attributes":{"day":"7","periods":"10:00\/18:00"}}],"WeightLimit":{"@attributes":{"WeightMin":"0","WeightMax":"100"}}},"На Кирова":{"@attributes":{"Code":"TOM9","Status":"ACTIVE","PostalCode":"634041","Name":"На Кирова","CountryCode":"1","countryCodeIso":"RU","CountryName":"Россия","RegionCode":"53","RegionName":"Томская обл.","CityCode":"269","City":"Томск","WorkTime":"Пн-Пт 10:00-20:00, Сб-Вс 10:00-18:00","Address":"ул. Красноармейская, 96","FullAddress":"Россия, Томская обл., Томск, ул. Красноармейская, 96","AddressComment":"На пересечении пр. Кирова и ул. Красноармейская, вход в офис справа от здания со стороны ул. Красноармейская","Phone":"+79138533396","Email":"yu.grishaev@cdek.ru","Note":"На пересечении пр. Кирова и ул. Красноармейская, вход в офис справа от здания со стороны ул. Красноармейская","coordX":"84.965838","coordY":"56.467038","Type":"PVZ","ownerCode":"cdek","IsDressingRoom":"true","HaveCashless":"true","HaveCash":"true","AllowedCod":"true","TakeOnly":"false","IsHandout":"true","IsReception":"true","NearestStation":"Пр-т Кирова","MetroStation":"","Site":"","Fulfillment":"false","FiasGuid":"e3b0eae8-a4ce-4779-ae04-5c0797de66be"},"PhoneDetail":{"@attributes":{"number":"+79138533396"}},"OfficeImage":[{"@attributes":{"url":"https:\/\/pvzimage.cdek.ru\/images\/1547\/747_4_TOM9"}},{"@attributes":{"url":"https:\/\/pvzimage.cdek.ru\/images\/1547\/750_7_TOM9"}},{"@attributes":{"url":"https:\/\/pvzimage.cdek.ru\/images\/1547\/744_1_TOM9"}},{"@attributes":{"url":"https:\/\/pvzimage.cdek.ru\/images\/1547\/749_6_TOM9"}},{"@attributes":{"url":"https:\/\/pvzimage.cdek.ru\/images\/1547\/748_5_TOM9"}},{"@attributes":{"url":"https:\/\/pvzimage.cdek.ru\/images\/1547\/745_2_TOM9"}},{"@attributes":{"url":"https:\/\/pvzimage.cdek.ru\/images\/1547\/746_3_TOM9"}}],"WorkTimeY":[{"@attributes":{"day":"1","periods":"10:00\/20:00"}},{"@attributes":{"day":"2","periods":"10:00\/20:00"}},{"@attributes":{"day":"3","periods":"10:00\/20:00"}},{"@attributes":{"day":"4","periods":"10:00\/20:00"}},{"@attributes":{"day":"5","periods":"10:00\/20:00"}},{"@attributes":{"day":"6","periods":"10:00\/18:00"}},{"@attributes":{"day":"7","periods":"10:00\/18:00"}}]},"На Лазо":{"@attributes":{"Code":"TOM15","Status":"ACTIVE","PostalCode":"634063","Name":"На Лазо","CountryCode":"1","countryCodeIso":"RU","CountryName":"Россия","RegionCode":"53","RegionName":"Томская обл.","CityCode":"269","City":"Томск","WorkTime":"Пн-Пт 10:00-20:00, Сб-Вс 10:00-18:00","Address":"ул. Сергея Лазо, 23, 54","FullAddress":"Россия, Томская обл., Томск, ул. Сергея Лазо, 23, 54","AddressComment":"Выйти на Остановке 14 лицей по ул. Сергея Лазо. За остановкой находится 3 этажное здание ,вход в ПВЗ с центрального крыльца","Phone":"+73822683772","Email":"a.tishkov@cdek.ru","Note":"Выйти на Остановке 14 лицей по ул. Сергея Лазо. За остановкой находится 3 этажное здание ,вход в ПВЗ с центрального крыльца","coordX":"85.04005","coordY":"56.517947","Type":"PVZ","ownerCode":"cdek","IsDressingRoom":"true","HaveCashless":"true","HaveCash":"true","AllowedCod":"true","TakeOnly":"false","IsHandout":"true","IsReception":"true","NearestStation":"14 лицей","MetroStation":"","Site":"","Fulfillment":"false","FiasGuid":"e3b0eae8-a4ce-4779-ae04-5c0797de66be"},"PhoneDetail":{"@attributes":{"number":"+73822683772"}},"OfficeImage":[{"@attributes":{"url":"https:\/\/pvzimage.cdek.ru\/images\/2678\/33518_image"}},{"@attributes":{"url":"https:\/\/pvzimage.cdek.ru\/images\/2678\/33516_image"}},{"@attributes":{"url":"https:\/\/pvzimage.cdek.ru\/images\/2678\/33515_image"}}],"WorkTimeY":[{"@attributes":{"day":"1","periods":"10:00\/20:00"}},{"@attributes":{"day":"2","periods":"10:00\/20:00"}},{"@attributes":{"day":"3","periods":"10:00\/20:00"}},{"@attributes":{"day":"4","periods":"10:00\/20:00"}},{"@attributes":{"day":"5","periods":"10:00\/20:00"}},{"@attributes":{"day":"6","periods":"10:00\/18:00"}},{"@attributes":{"day":"7","periods":"10:00\/18:00"}}]},"7298 Постамат ОМНИСДЭК":{"@attributes":{"Code":"TOM40","Status":"ACTIVE","PostalCode":"634062","Name":"7298 Постамат ОМНИСДЭК","CountryCode":"1","countryCodeIso":"RU","CountryName":"Россия","RegionCode":"53","RegionName":"Томская обл.","CityCode":"269","City":"Томск","WorkTime":"Пн-Вс 09:00-22:00","Address":"Иркутский тракт, 128","FullAddress":"Россия, Томская обл., Томск, Иркутский тракт, 128","AddressComment":"Мария-Ра","Phone":"+78007753553","Email":"","Note":"Мария-Ра","coordX":"85.045897","coordY":"56.513785","Type":"POSTAMAT","ownerCode":"cdek","IsDressingRoom":"false","HaveCashless":"true","HaveCash":"false","AllowedCod":"true","TakeOnly":"false","IsHandout":"true","IsReception":"true","NearestStation":"Рынок Северный","MetroStation":"","Site":"","Fulfillment":"false","FiasGuid":"e3b0eae8-a4ce-4779-ae04-5c0797de66be"},"PhoneDetail":{"@attributes":{"number":"+78007753553"}},"OfficeImage":[{"@attributes":{"url":"https:\/\/pvzimage.cdek.ru\/images\/8882\/44262_image"}},{"@attributes":{"url":"https:\/\/pvzimage.cdek.ru\/images\/8882\/44472_image"}}],"WorkTimeY":[{"@attributes":{"day":"1","periods":"09:00\/22:00"}},{"@attributes":{"day":"2","periods":"09:00\/22:00"}},{"@attributes":{"day":"3","periods":"09:00\/22:00"}},{"@attributes":{"day":"4","periods":"09:00\/22:00"}},{"@attributes":{"day":"5","periods":"09:00\/22:00"}},{"@attributes":{"day":"6","periods":"09:00\/22:00"}},{"@attributes":{"day":"7","periods":"09:00\/22:00"}}],"WeightLimit":{"@attributes":{"WeightMin":"0","WeightMax":"30"}},"Dimensions":{"@attributes":{"depth":"40.5","height":"36.5","width":"64.5"}}},"На Говорова 27А":{"@attributes":{"Code":"TOM43","Status":"ACTIVE","PostalCode":"634059","Name":"На Говорова 27А","CountryCode":"1","countryCodeIso":"RU","CountryName":"Россия","RegionCode":"53","RegionName":"Томская обл.","CityCode":"269","City":"Томск","WorkTime":"Пн-Пт 09:00-20:00, Сб-Вс 10:00-18:00","Address":"ул. Говорова, 27А","FullAddress":"Россия, Томская обл., Томск, ул. Говорова, 27А","AddressComment":"Автобусная остановка \"Интернационалистов\", от остановки пройти 150м по ул. Говорова , находимся в одном здании с магазином \"Ярче\".","Phone":"+79913917371","Email":"s.kazakov@cdek.ru","Note":"Автобусная остановка \"Интернационалистов\", от остановки пройти 150м по ул. Говорова , находимся в одном здании с магазином \"Ярче\".","coordX":"84.991199","coordY":"56.513969","Type":"PVZ","ownerCode":"cdek","IsDressingRoom":"true","HaveCashless":"true","HaveCash":"true","AllowedCod":"true","TakeOnly":"false","IsHandout":"true","IsReception":"true","NearestStation":"Интернационалистов","MetroStation":"","Site":"","Fulfillment":"false","FiasGuid":"e3b0eae8-a4ce-4779-ae04-5c0797de66be"},"PhoneDetail":{"@attributes":{"number":"+79913917371"}},"OfficeImage":[{"@attributes":{"url":"https:\/\/pvzimage.cdek.ru\/images\/9336\/46556_image"}},{"@attributes":{"url":"https:\/\/pvzimage.cdek.ru\/images\/9336\/46558_image"}},{"@attributes":{"url":"https:\/\/pvzimage.cdek.ru\/images\/9336\/46560_image"}},{"@attributes":{"url":"https:\/\/pvzimage.cdek.ru\/images\/9336\/46562_image"}},{"@attributes":{"url":"https:\/\/pvzimage.cdek.ru\/images\/9336\/46564_image"}},{"@attributes":{"url":"https:\/\/pvzimage.cdek.ru\/images\/9336\/46566_image"}},{"@attributes":{"url":"https:\/\/pvzimage.cdek.ru\/images\/9336\/46568_image"}},{"@attributes":{"url":"https:\/\/pvzimage.cdek.ru\/images\/9336\/46570_image"}},{"@attributes":{"url":"https:\/\/pvzimage.cdek.ru\/images\/9336\/46572_image"}},{"@attributes":{"url":"https:\/\/pvzimage.cdek.ru\/images\/9336\/47220_image"}},{"@attributes":{"url":"https:\/\/pvzimage.cdek.ru\/images\/9336\/47222_image"}}],"WorkTimeY":[{"@attributes":{"day":"1","periods":"09:00\/20:00"}},{"@attributes":{"day":"2","periods":"09:00\/20:00"}},{"@attributes":{"day":"3","periods":"09:00\/20:00"}},{"@attributes":{"day":"4","periods":"09:00\/20:00"}},{"@attributes":{"day":"5","periods":"09:00\/20:00"}},{"@attributes":{"day":"6","periods":"10:00\/18:00"}},{"@attributes":{"day":"7","periods":"10:00\/18:00"}}]},"На Марины Цветаевой, 15":{"@attributes":{"Code":"TOM26","Status":"ACTIVE","PostalCode":"634050","Name":"На Марины Цветаевой, 15","CountryCode":"1","countryCodeIso":"RU","CountryName":"Россия","RegionCode":"53","RegionName":"Томская обл.","CityCode":"269","City":"Томск","WorkTime":"Пн-Пт 10:00-20:00, Сб-Вс 10:00-18:00","Address":"ул. Марины Цветаевой, 15","FullAddress":"Россия, Томская обл., Томск, ул. Марины Цветаевой, 15","AddressComment":"Выйти на остановке Марины Цветаевой 15,  повернуть налево, потом направо и дойти до угла дома","Phone":"+79521582499","Email":"g.memeshkin@cdek.ru","Note":"Выйти на остановке Марины Цветаевой 15,  повернуть налево, потом направо и дойти до угла дома","coordX":"84.900954","coordY":"56.469362","Type":"PVZ","ownerCode":"cdek","IsDressingRoom":"true","HaveCashless":"true","HaveCash":"true","AllowedCod":"true","TakeOnly":"false","IsHandout":"true","IsReception":"true","NearestStation":"ул. Марины Цветаевой, 15","MetroStation":"","Site":"","Fulfillment":"false","FiasGuid":"e3b0eae8-a4ce-4779-ae04-5c0797de66be"},"PhoneDetail":{"@attributes":{"number":"+79521582499"}},"OfficeImage":[{"@attributes":{"url":"https:\/\/pvzimage.cdek.ru\/images\/7794\/27033_image"}},{"@attributes":{"url":"https:\/\/pvzimage.cdek.ru\/images\/7794\/27035_image"}},{"@attributes":{"url":"https:\/\/pvzimage.cdek.ru\/images\/7794\/27037_image"}}],"WorkTimeY":[{"@attributes":{"day":"1","periods":"10:00\/20:00"}},{"@attributes":{"day":"2","periods":"10:00\/20:00"}},{"@attributes":{"day":"3","periods":"10:00\/20:00"}},{"@attributes":{"day":"4","periods":"10:00\/20:00"}},{"@attributes":{"day":"5","periods":"10:00\/20:00"}},{"@attributes":{"day":"6","periods":"10:00\/18:00"}},{"@attributes":{"day":"7","periods":"10:00\/18:00"}}]},"На Гагарина":{"@attributes":{"Code":"TOM7","Status":"ACTIVE","PostalCode":"634050","Name":"На Гагарина","CountryCode":"1","countryCodeIso":"RU","CountryName":"Россия","RegionCode":"53","RegionName":"Томская обл.","CityCode":"269","City":"Томск","WorkTime":"Пн-Пт 10:00-20:00, Сб-Вс 10:00-18:00","Address":"ул. Гагарина, 7","FullAddress":"Россия, Томская обл., Томск, ул. Гагарина, 7","AddressComment":"ТЦ\"Аврора\", цокольный этаж.","Phone":"+79913915606, +79832320852, +73822320852","Email":"y.grigoryev@cdek.ru","Note":"ТЦ\"Аврора\", цокольный этаж.","coordX":"84.951195","coordY":"56.483145","Type":"PVZ","ownerCode":"cdek","IsDressingRoom":"true","HaveCashless":"true","HaveCash":"true","AllowedCod":"true","TakeOnly":"false","IsHandout":"true","IsReception":"true","NearestStation":"ТЮЗ","MetroStation":"","Site":"","Fulfillment":"false","FiasGuid":"e3b0eae8-a4ce-4779-ae04-5c0797de66be"},"PhoneDetail":[{"@attributes":{"number":"+79913915606"}},{"@attributes":{"number":"+79832320852"}},{"@attributes":{"number":"+73822320852"}}],"OfficeImage":[{"@attributes":{"url":"https:\/\/pvzimage.cdek.ru\/images\/1365\/235_1_TOM7"}},{"@attributes":{"url":"https:\/\/pvzimage.cdek.ru\/images\/1365\/236_2_TOM7"}},{"@attributes":{"url":"https:\/\/pvzimage.cdek.ru\/images\/1365\/237_3_TOM7"}}],"WorkTimeY":[{"@attributes":{"day":"1","periods":"10:00\/20:00"}},{"@attributes":{"day":"2","periods":"10:00\/20:00"}},{"@attributes":{"day":"3","periods":"10:00\/20:00"}},{"@attributes":{"day":"4","periods":"10:00\/20:00"}},{"@attributes":{"day":"5","periods":"10:00\/20:00"}},{"@attributes":{"day":"6","periods":"10:00\/18:00"}},{"@attributes":{"day":"7","periods":"10:00\/18:00"}}],"WeightLimit":{"@attributes":{"WeightMin":"0","WeightMax":"100"}}},"6580 Постамат ОМНИСДЭК":{"@attributes":{"Code":"TOM34","Status":"ACTIVE","PostalCode":"634509","Name":"6580 Постамат ОМНИСДЭК","CountryCode":"1","countryCodeIso":"RU","CountryName":"Россия","RegionCode":"53","RegionName":"Томская обл.","CityCode":"269","City":"Томск","WorkTime":"Пн-Вс 10:00-22:00","Address":"ул. Виталия Грачёва, 2Б","FullAddress":"Россия, Томская обл., Томск, ул. Виталия Грачёва, 2Б","AddressComment":"Магазин \"Есть повод\", посёлок Зональная Станция","Phone":"+78007753553","Email":"","Note":"Магазин \"Есть повод\", посёлок Зональная Станция","coordX":"85.024823","coordY":"56.442588","Type":"POSTAMAT","ownerCode":"cdek","IsDressingRoom":"false","HaveCashless":"true","HaveCash":"false","AllowedCod":"true","TakeOnly":"false","IsHandout":"true","IsReception":"true","NearestStation":"ул. Виталия Грачёва","MetroStation":"","Site":"","Fulfillment":"false","FiasGuid":"e3b0eae8-a4ce-4779-ae04-5c0797de66be"},"PhoneDetail":{"@attributes":{"number":"+78007753553"}},"OfficeImage":[{"@attributes":{"url":"https:\/\/pvzimage.cdek.ru\/images\/8404\/35814_image"}},{"@attributes":{"url":"https:\/\/pvzimage.cdek.ru\/images\/8404\/35818_image"}}],"WorkTimeY":[{"@attributes":{"day":"1","periods":"10:00\/22:00"}},{"@attributes":{"day":"2","periods":"10:00\/22:00"}},{"@attributes":{"day":"3","periods":"10:00\/22:00"}},{"@attributes":{"day":"4","periods":"10:00\/22:00"}},{"@attributes":{"day":"5","periods":"10:00\/22:00"}},{"@attributes":{"day":"6","periods":"10:00\/22:00"}},{"@attributes":{"day":"7","periods":"10:00\/22:00"}}],"WeightLimit":{"@attributes":{"WeightMin":"0","WeightMax":"30"}},"Dimensions":{"@attributes":{"depth":"40.5","height":"36.5","width":"64.5"}}},"На Ленина":{"@attributes":{"Code":"TOM3","Status":"ACTIVE","PostalCode":"634009","Name":"На Ленина","CountryCode":"1","countryCodeIso":"RU","CountryName":"Россия","RegionCode":"53","RegionName":"Томская обл.","CityCode":"269","City":"Томск","WorkTime":"Пн-Пт 10:00-20:00, Сб-Вс 10:00-18:00","Address":"пр-т Ленина, 190\/2, крыльцо Б, 2","FullAddress":"Россия, Томская обл., Томск, пр-т Ленина, 190\/2, крыльцо Б, 2","AddressComment":"БЦ \"Яромир\", крыльцо Б, домофон 2, 1 этаж","Phone":"+73822400215","Email":"m.masalkina@cdek.ru","Note":"БЦ \"Яромир\", крыльцо Б, домофон 2, 1 этаж","coordX":"84.9465332","coordY":"56.508049","Type":"PVZ","ownerCode":"cdek","IsDressingRoom":"true","HaveCashless":"true","HaveCash":"true","AllowedCod":"true","TakeOnly":"false","IsHandout":"true","IsReception":"true","NearestStation":"Дрож завод","MetroStation":"","Site":"https:\/\/www.cdek.ru\/contacts\/g_tomsk_pr_lenina_d1902_krylco_b_of12.html","Fulfillment":"false","FiasGuid":"e3b0eae8-a4ce-4779-ae04-5c0797de66be"},"PhoneDetail":{"@attributes":{"number":"+73822400215"}},"OfficeImage":[{"@attributes":{"url":"https:\/\/pvzimage.cdek.ru\/images\/1133\/33492_image"}},{"@attributes":{"url":"https:\/\/pvzimage.cdek.ru\/images\/1133\/33510_image"}},{"@attributes":{"url":"https:\/\/pvzimage.cdek.ru\/images\/1133\/33512_image"}},{"@attributes":{"url":"https:\/\/pvzimage.cdek.ru\/images\/1133\/33500_image"}},{"@attributes":{"url":"https:\/\/pvzimage.cdek.ru\/images\/1133\/33508_image"}}],"WorkTimeY":[{"@attributes":{"day":"1","periods":"10:00\/20:00"}},{"@attributes":{"day":"2","periods":"10:00\/20:00"}},{"@attributes":{"day":"3","periods":"10:00\/20:00"}},{"@attributes":{"day":"4","periods":"10:00\/20:00"}},{"@attributes":{"day":"5","periods":"10:00\/20:00"}},{"@attributes":{"day":"6","periods":"10:00\/18:00"}},{"@attributes":{"day":"7","periods":"10:00\/18:00"}}],"WeightLimit":{"@attributes":{"WeightMin":"0","WeightMax":"35"}}},"7291 Постамат ОМНИСДЭК":{"@attributes":{"Code":"TOM36","Status":"ACTIVE","PostalCode":"634009","Name":"7291 Постамат ОМНИСДЭК","CountryCode":"1","countryCodeIso":"RU","CountryName":"Россия","RegionCode":"53","RegionName":"Томская обл.","CityCode":"269","City":"Томск","WorkTime":"Пн-Вс 08:00-22:00","Address":"ул. Карла Маркса, 34","FullAddress":"Россия, Томская обл., Томск, ул. Карла Маркса, 34","AddressComment":"Мария-Ра","Phone":"+78007753553","Email":"","Note":"Мария-Ра","coordX":"84.944666","coordY":"56.494674","Type":"POSTAMAT","ownerCode":"cdek","IsDressingRoom":"false","HaveCashless":"true","HaveCash":"false","AllowedCod":"true","TakeOnly":"false","IsHandout":"true","IsReception":"true","NearestStation":"Речной вокзал","MetroStation":"","Site":"","Fulfillment":"false","FiasGuid":"e3b0eae8-a4ce-4779-ae04-5c0797de66be"},"PhoneDetail":{"@attributes":{"number":"+78007753553"}},"OfficeImage":[{"@attributes":{"url":"https:\/\/pvzimage.cdek.ru\/images\/8692\/40782_image"}},{"@attributes":{"url":"https:\/\/pvzimage.cdek.ru\/images\/8692\/40784_image"}}],"WorkTimeY":[{"@attributes":{"day":"1","periods":"08:00\/22:00"}},{"@attributes":{"day":"2","periods":"08:00\/22:00"}},{"@attributes":{"day":"3","periods":"08:00\/22:00"}},{"@attributes":{"day":"4","periods":"08:00\/22:00"}},{"@attributes":{"day":"5","periods":"08:00\/22:00"}},{"@attributes":{"day":"6","periods":"08:00\/22:00"}},{"@attributes":{"day":"7","periods":"08:00\/22:00"}}],"WeightLimit":{"@attributes":{"WeightMin":"0","WeightMax":"30"}},"Dimensions":{"@attributes":{"depth":"40.5","height":"36.5","width":"64.5"}}},"На Енисейской":{"@attributes":{"Code":"TOM11","Status":"ACTIVE","PostalCode":"634021","Name":"На Енисейской","CountryCode":"1","countryCodeIso":"RU","CountryName":"Россия","RegionCode":"53","RegionName":"Томская обл.","CityCode":"269","City":"Томск","WorkTime":"Пн-Пт 10:00-20:00, Сб-Вс 10:00-18:00","Address":"ул. Енисейская, 37, 105","FullAddress":"Россия, Томская обл., Томск, ул. Енисейская, 37, 105","AddressComment":"4-хэтажное офисное здание по диагонали от ТЦ Город\/Палата. Ближайшая остановка \"ГРЭС\".","Phone":"+73822283815","Email":"tomsk7@cdek.ru","Note":"4-хэтажное офисное здание по диагонали от ТЦ Город\/Палата. Ближайшая остановка \"ГРЭС\".","coordX":"84.989295","coordY":"56.47078","Type":"PVZ","ownerCode":"cdek","IsDressingRoom":"true","HaveCashless":"true","HaveCash":"true","AllowedCod":"true","TakeOnly":"false","IsHandout":"true","IsReception":"true","NearestStation":"Шевченко","MetroStation":"","Site":"","Fulfillment":"false","FiasGuid":"e3b0eae8-a4ce-4779-ae04-5c0797de66be"},"PhoneDetail":{"@attributes":{"number":"+73822283815"}},"OfficeImage":[{"@attributes":{"url":"https:\/\/pvzimage.cdek.ru\/images\/1687\/1220_4_TOM11"}},{"@attributes":{"url":"https:\/\/pvzimage.cdek.ru\/images\/1687\/1222_6_TOM11"}},{"@attributes":{"url":"https:\/\/pvzimage.cdek.ru\/images\/1687\/1221_5_TOM11"}},{"@attributes":{"url":"https:\/\/pvzimage.cdek.ru\/images\/1687\/1219_3_TOM11"}},{"@attributes":{"url":"https:\/\/pvzimage.cdek.ru\/images\/1687\/1218_2_TOM11"}},{"@attributes":{"url":"https:\/\/pvzimage.cdek.ru\/images\/1687\/1217_1_TOM11"}}],"WorkTimeY":[{"@attributes":{"day":"1","periods":"10:00\/20:00"}},{"@attributes":{"day":"2","periods":"10:00\/20:00"}},{"@attributes":{"day":"3","periods":"10:00\/20:00"}},{"@attributes":{"day":"4","periods":"10:00\/20:00"}},{"@attributes":{"day":"5","periods":"10:00\/20:00"}},{"@attributes":{"day":"6","periods":"10:00\/18:00"}},{"@attributes":{"day":"7","periods":"10:00\/18:00"}}],"WeightLimit":{"@attributes":{"WeightMin":"0","WeightMax":"35"}}},"На Фрунзе 124":{"@attributes":{"Code":"TOM27","Status":"ACTIVE","PostalCode":"634021","Name":"На Фрунзе 124","CountryCode":"1","countryCodeIso":"RU","CountryName":"Россия","RegionCode":"53","RegionName":"Томская обл.","CityCode":"269","City":"Томск","WorkTime":"Пн-Пт 10:00-20:00, Сб-Вс 10:00-18:00","Address":"пр-т Фрунзе, 124","FullAddress":"Россия, Томская обл., Томск, пр-т Фрунзе, 124","AddressComment":"Помещение справа от магазина \"Абрикос\". Напротив БЦ \"Красное знамя\"","Phone":"+79009232200","Email":"k.suhanov@cdek.ru","Note":"Помещение справа от магазина \"Абрикос\". Напротив БЦ \"Красное знамя\"","coordX":"84.9875","coordY":"56.476355","Type":"PVZ","ownerCode":"cdek","IsDressingRoom":"true","HaveCashless":"true","HaveCash":"true","AllowedCod":"true","TakeOnly":"false","IsHandout":"true","IsReception":"true","NearestStation":"Фрунзенский рынок, Шевченко","MetroStation":"","Site":"","Fulfillment":"false","FiasGuid":"e3b0eae8-a4ce-4779-ae04-5c0797de66be"},"PhoneDetail":{"@attributes":{"number":"+79009232200"}},"OfficeImage":[{"@attributes":{"url":"https:\/\/pvzimage.cdek.ru\/images\/7800\/27099_image"}},{"@attributes":{"url":"https:\/\/pvzimage.cdek.ru\/images\/7800\/27094_image"}},{"@attributes":{"url":"https:\/\/pvzimage.cdek.ru\/images\/7800\/27097_image"}},{"@attributes":{"url":"https:\/\/pvzimage.cdek.ru\/images\/7800\/27091_image"}},{"@attributes":{"url":"https:\/\/pvzimage.cdek.ru\/images\/7800\/27095_image"}},{"@attributes":{"url":"https:\/\/pvzimage.cdek.ru\/images\/7800\/27101_image"}},{"@attributes":{"url":"https:\/\/pvzimage.cdek.ru\/images\/7800\/27103_image"}}],"WorkTimeY":[{"@attributes":{"day":"1","periods":"10:00\/20:00"}},{"@attributes":{"day":"2","periods":"10:00\/20:00"}},{"@attributes":{"day":"3","periods":"10:00\/20:00"}},{"@attributes":{"day":"4","periods":"10:00\/20:00"}},{"@attributes":{"day":"5","periods":"10:00\/20:00"}},{"@attributes":{"day":"6","periods":"10:00\/18:00"}},{"@attributes":{"day":"7","periods":"10:00\/18:00"}}],"WeightLimit":{"@attributes":{"WeightMin":"0","WeightMax":"50"}}},"7280 Постамат ОМНИСДЭК":{"@attributes":{"Code":"TOM39","Status":"ACTIVE","PostalCode":"634034","Name":"7280 Постамат ОМНИСДЭК","CountryCode":"1","countryCodeIso":"RU","CountryName":"Россия","RegionCode":"53","RegionName":"Томская обл.","CityCode":"269","City":"Томск","WorkTime":"Пн-Вс 09:00-22:00","Address":"ул. Красноармейская, 122","FullAddress":"Россия, Томская обл., Томск, ул. Красноармейская, 122","AddressComment":"Мария-Ра","Phone":"+78007753553","Email":"","Note":"Мария-Ра","coordX":"84.97211","coordY":"56.461342","Type":"POSTAMAT","ownerCode":"cdek","IsDressingRoom":"false","HaveCashless":"true","HaveCash":"false","AllowedCod":"true","TakeOnly":"false","IsHandout":"true","IsReception":"true","NearestStation":"Дворец Спорта","MetroStation":"","Site":"","Fulfillment":"false","FiasGuid":"e3b0eae8-a4ce-4779-ae04-5c0797de66be"},"PhoneDetail":{"@attributes":{"number":"+78007753553"}},"OfficeImage":[{"@attributes":{"url":"https:\/\/pvzimage.cdek.ru\/images\/8745\/43100_image"}},{"@attributes":{"url":"https:\/\/pvzimage.cdek.ru\/images\/8745\/43104_image"}},{"@attributes":{"url":"https:\/\/pvzimage.cdek.ru\/images\/8745\/43102_image"}}],"WorkTimeY":[{"@attributes":{"day":"1","periods":"09:00\/22:00"}},{"@attributes":{"day":"2","periods":"09:00\/22:00"}},{"@attributes":{"day":"3","periods":"09:00\/22:00"}},{"@attributes":{"day":"4","periods":"09:00\/22:00"}},{"@attributes":{"day":"5","periods":"09:00\/22:00"}},{"@attributes":{"day":"6","periods":"09:00\/22:00"}},{"@attributes":{"day":"7","periods":"09:00\/22:00"}}],"WeightLimit":{"@attributes":{"WeightMin":"0","WeightMax":"30"}},"Dimensions":{"@attributes":{"depth":"40.5","height":"36.5","width":"64.5"}}},"7297 Постамат ОМНИСДЭК":{"@attributes":{"Code":"TOM35","Status":"ACTIVE","PostalCode":"634059","Name":"7297 Постамат ОМНИСДЭК","CountryCode":"1","countryCodeIso":"RU","CountryName":"Россия","RegionCode":"53","RegionName":"Томская обл.","CityCode":"269","City":"Томск","WorkTime":"Пн-Вс 08:00-23:00","Address":"ул. Говорова, 41, пом.16-61","FullAddress":"Россия, Томская обл., Томск, ул. Говорова, 41, пом.16-61","AddressComment":"Мария-Ра","Phone":"+78007753553","Email":"","Note":"Мария-Ра","coordX":"84.993912","coordY":"56.515871","Type":"POSTAMAT","ownerCode":"cdek","IsDressingRoom":"false","HaveCashless":"true","HaveCash":"false","AllowedCod":"true","TakeOnly":"false","IsHandout":"true","IsReception":"true","NearestStation":"Школа №55","MetroStation":"","Site":"","Fulfillment":"false","FiasGuid":"e3b0eae8-a4ce-4779-ae04-5c0797de66be"},"PhoneDetail":{"@attributes":{"number":"+78007753553"}},"OfficeImage":[{"@attributes":{"url":"https:\/\/pvzimage.cdek.ru\/images\/8678\/40618_image"}},{"@attributes":{"url":"https:\/\/pvzimage.cdek.ru\/images\/8678\/40398_image"}}],"WorkTimeY":[{"@attributes":{"day":"1","periods":"08:00\/23:00"}},{"@attributes":{"day":"2","periods":"08:00\/23:00"}},{"@attributes":{"day":"3","periods":"08:00\/23:00"}},{"@attributes":{"day":"4","periods":"08:00\/23:00"}},{"@attributes":{"day":"5","periods":"08:00\/23:00"}},{"@attributes":{"day":"6","periods":"08:00\/23:00"}},{"@attributes":{"day":"7","periods":"08:00\/23:00"}}],"WeightLimit":{"@attributes":{"WeightMin":"0","WeightMax":"30"}},"Dimensions":{"@attributes":{"depth":"40.5","height":"36.5","width":"64.5"}}},"На Большой Подгорной, 87":{"@attributes":{"Code":"TOM28","Status":"ACTIVE","PostalCode":"634009","Name":"На Большой Подгорной, 87","CountryCode":"1","countryCodeIso":"RU","CountryName":"Россия","RegionCode":"53","RegionName":"Томская обл.","CityCode":"269","City":"Томск","WorkTime":"Пн-Пт 10:00-20:00, Сб-Вс 10:00-18:00","Address":"ул. Большая Подгорная, 87, 33","FullAddress":"Россия, Томская обл., Томск, ул. Большая Подгорная, 87, 33","AddressComment":"Главный вход в офис со стороны ул. Дальне-Ключевская рядом с магазином Абрикос, так же есть дополнительные входы с стороны ул. Большая Подгорная, пер. Островского, офис 33, домофон 33.","Phone":"+73822607776","Email":"a.lopuhov@cdek.ru","Note":"Главный вход в офис со стороны ул. Дальне-Ключевская рядом с магазином Абрикос, так же есть дополнительные входы с стороны ул. Большая Подгорная, пер. Островского, офис 33, домофон 33.","coordX":"84.954009","coordY":"56.503409","Type":"PVZ","ownerCode":"cdek","IsDressingRoom":"true","HaveCashless":"true","HaveCash":"true","AllowedCod":"true","TakeOnly":"false","IsHandout":"true","IsReception":"true","NearestStation":"Дальне-Ключевская, Старокаштачная","MetroStation":"","Site":"","Fulfillment":"false","FiasGuid":"e3b0eae8-a4ce-4779-ae04-5c0797de66be"},"PhoneDetail":{"@attributes":{"number":"+73822607776"}},"OfficeImage":[{"@attributes":{"url":"https:\/\/pvzimage.cdek.ru\/images\/7813\/27205_image"}},{"@attributes":{"url":"https:\/\/pvzimage.cdek.ru\/images\/7813\/27209_image"}},{"@attributes":{"url":"https:\/\/pvzimage.cdek.ru\/images\/7813\/27211_image"}},{"@attributes":{"url":"https:\/\/pvzimage.cdek.ru\/images\/7813\/27207_image"}}],"WorkTimeY":[{"@attributes":{"day":"1","periods":"10:00\/20:00"}},{"@attributes":{"day":"2","periods":"10:00\/20:00"}},{"@attributes":{"day":"3","periods":"10:00\/20:00"}},{"@attributes":{"day":"4","periods":"10:00\/20:00"}},{"@attributes":{"day":"5","periods":"10:00\/20:00"}},{"@attributes":{"day":"6","periods":"10:00\/18:00"}},{"@attributes":{"day":"7","periods":"10:00\/18:00"}}]},"На Нахимова":{"@attributes":{"Code":"TOM10","Status":"ACTIVE","PostalCode":"634028","Name":"На Нахимова","CountryCode":"1","countryCodeIso":"RU","CountryName":"Россия","RegionCode":"53","RegionName":"Томская обл.","CityCode":"269","City":"Томск","WorkTime":"Пн-Вс 08:00-21:00","Address":"ул. Нахимова, 8  стр. 37","FullAddress":"Россия, Томская обл., Томск, ул. Нахимова, 8  стр. 37","AddressComment":"Въезд с ул. Учебная","Phone":"+73822789560","Email":"tomsk_klient@cdek.ru","Note":"Въезд с ул. Учебная","coordX":"84.957139","coordY":"56.458132","Type":"PVZ","ownerCode":"cdek","IsDressingRoom":"true","HaveCashless":"true","HaveCash":"true","AllowedCod":"true","TakeOnly":"false","IsHandout":"true","IsReception":"true","NearestStation":"Белинского","MetroStation":"","Site":"","Fulfillment":"false","FiasGuid":"e3b0eae8-a4ce-4779-ae04-5c0797de66be"},"PhoneDetail":{"@attributes":{"number":"+73822789560"}},"OfficeImage":[{"@attributes":{"url":"https:\/\/pvzimage.cdek.ru\/images\/1674\/27467_image"}},{"@attributes":{"url":"https:\/\/pvzimage.cdek.ru\/images\/1674\/27469_image"}},{"@attributes":{"url":"https:\/\/pvzimage.cdek.ru\/images\/1674\/3099_1_TOM10"}},{"@attributes":{"url":"https:\/\/pvzimage.cdek.ru\/images\/1674\/27471_image"}},{"@attributes":{"url":"https:\/\/pvzimage.cdek.ru\/images\/1674\/27473_image"}}],"WorkTimeY":[{"@attributes":{"day":"1","periods":"08:00\/21:00"}},{"@attributes":{"day":"2","periods":"08:00\/21:00"}},{"@attributes":{"day":"3","periods":"08:00\/21:00"}},{"@attributes":{"day":"4","periods":"08:00\/21:00"}},{"@attributes":{"day":"5","periods":"08:00\/21:00"}},{"@attributes":{"day":"6","periods":"08:00\/21:00"}},{"@attributes":{"day":"7","periods":"08:00\/21:00"}}]},"На Фрунзе":{"@attributes":{"Code":"TOM22","Status":"ACTIVE","PostalCode":"634061","Name":"На Фрунзе","CountryCode":"1","countryCodeIso":"RU","CountryName":"Россия","RegionCode":"53","RegionName":"Томская обл.","CityCode":"269","City":"Томск","WorkTime":"Пн-Пт 09:00-21:00, Сб-Вс 10:00-18:00","Address":"пр.Фрунзе, 86","FullAddress":"Россия, Томская обл., Томск, пр.Фрунзе, 86","AddressComment":"Пересечение улиц Красноармейская и Фрунзе, вход ТЦ Европа со стороны ул. Красноармейская. Остановка общественного транспорта ЦОТ","Phone":"+79009221100","Email":"k.suhanov@cdek.ru","Note":"Пересечение улиц Красноармейская и Фрунзе, вход ТЦ Европа со стороны ул. Красноармейская. Остановка общественного транспорта ЦОТ","coordX":"84.9662971","coordY":"56.476687","Type":"PVZ","ownerCode":"cdek","IsDressingRoom":"true","HaveCashless":"true","HaveCash":"true","AllowedCod":"true","TakeOnly":"false","IsHandout":"true","IsReception":"true","NearestStation":"Суханов Кирилл Игоревич","MetroStation":"","Site":"","Fulfillment":"false","FiasGuid":"e3b0eae8-a4ce-4779-ae04-5c0797de66be"},"PhoneDetail":{"@attributes":{"number":"+79009221100"}},"OfficeImage":[{"@attributes":{"url":"https:\/\/pvzimage.cdek.ru\/images\/6399\/16649_image"}},{"@attributes":{"url":"https:\/\/pvzimage.cdek.ru\/images\/6399\/16653_image"}},{"@attributes":{"url":"https:\/\/pvzimage.cdek.ru\/images\/6399\/16657_image"}},{"@attributes":{"url":"https:\/\/pvzimage.cdek.ru\/images\/6399\/16659_image"}},{"@attributes":{"url":"https:\/\/pvzimage.cdek.ru\/images\/6399\/16651_image"}},{"@attributes":{"url":"https:\/\/pvzimage.cdek.ru\/images\/6399\/16655_image"}},{"@attributes":{"url":"https:\/\/pvzimage.cdek.ru\/images\/6399\/16661_image"}}],"WorkTimeY":[{"@attributes":{"day":"1","periods":"09:00\/21:00"}},{"@attributes":{"day":"2","periods":"09:00\/21:00"}},{"@attributes":{"day":"3","periods":"09:00\/21:00"}},{"@attributes":{"day":"4","periods":"09:00\/21:00"}},{"@attributes":{"day":"5","periods":"09:00\/21:00"}},{"@attributes":{"day":"6","periods":"10:00\/18:00"}},{"@attributes":{"day":"7","periods":"10:00\/18:00"}}]},"6547 Постамат ОМНИСДЭК":{"@attributes":{"Code":"TOM33","Status":"ACTIVE","PostalCode":"634045","Name":"6547 Постамат ОМНИСДЭК","CountryCode":"1","countryCodeIso":"RU","CountryName":"Россия","RegionCode":"53","RegionName":"Томская обл.","CityCode":"269","City":"Томск","WorkTime":"Пн-Чт 11:00-23:00, Пт-Вс 10:00-23:00","Address":"ул. Мокрушина, 9","FullAddress":"Россия, Томская обл., Томск, ул. Мокрушина, 9","AddressComment":"Вход магазин \"Ярче\" и направо магазин \"Есть повод\"","Phone":"+78007753553","Email":"","Note":"Вход магазин \"Ярче\" и направо магазин \"Есть повод\"","coordX":"84.99022","coordY":"56.448638","Type":"POSTAMAT","ownerCode":"cdek","IsDressingRoom":"false","HaveCashless":"true","HaveCash":"false","AllowedCod":"true","TakeOnly":"false","IsHandout":"true","IsReception":"true","NearestStation":"Площадь Кукина","MetroStation":"","Site":"","Fulfillment":"false","FiasGuid":"e3b0eae8-a4ce-4779-ae04-5c0797de66be"},"PhoneDetail":{"@attributes":{"number":"+78007753553"}},"OfficeImage":[{"@attributes":{"url":"https:\/\/pvzimage.cdek.ru\/images\/8402\/35266_image"}},{"@attributes":{"url":"https:\/\/pvzimage.cdek.ru\/images\/8402\/35268_image"}}],"WorkTimeY":[{"@attributes":{"day":"1","periods":"11:00\/23:00"}},{"@attributes":{"day":"2","periods":"11:00\/23:00"}},{"@attributes":{"day":"3","periods":"11:00\/23:00"}},{"@attributes":{"day":"4","periods":"11:00\/23:00"}},{"@attributes":{"day":"5","periods":"10:00\/23:00"}},{"@attributes":{"day":"6","periods":"10:00\/23:00"}},{"@attributes":{"day":"7","periods":"10:00\/23:00"}}],"WeightLimit":{"@attributes":{"WeightMin":"0","WeightMax":"30"}},"Dimensions":{"@attributes":{"depth":"40.5","height":"36.5","width":"64.5"}}},"На Сибирской":{"@attributes":{"Code":"TOM24","Status":"ACTIVE","PostalCode":"634021","Name":"На Сибирской","CountryCode":"1","countryCodeIso":"RU","CountryName":"Россия","RegionCode":"53","RegionName":"Томская обл.","CityCode":"269","City":"Томск","WorkTime":"Пн-Пт 10:00-20:00, Сб-Вс 10:00-18:00","Address":"ул. Сибирская, 79А","FullAddress":"Россия, Томская обл., Томск, ул. Сибирская, 79А","AddressComment":"Здание находится напротив магазина \"Абрикос\"","Phone":"+79138536663, +73822336663","Email":"v.zapuskalov@cdek.ru","Note":"Здание находится напротив магазина \"Абрикос\"","coordX":"84.984345","coordY":"56.482225","Type":"PVZ","ownerCode":"cdek","IsDressingRoom":"true","HaveCashless":"true","HaveCash":"true","AllowedCod":"true","TakeOnly":"false","IsHandout":"true","IsReception":"true","NearestStation":"Школа-интернат","MetroStation":"","Site":"","Fulfillment":"false","FiasGuid":"e3b0eae8-a4ce-4779-ae04-5c0797de66be"},"PhoneDetail":[{"@attributes":{"number":"+79138536663"}},{"@attributes":{"number":"+73822336663"}}],"OfficeImage":[{"@attributes":{"url":"https:\/\/pvzimage.cdek.ru\/images\/7271\/20465_image"}},{"@attributes":{"url":"https:\/\/pvzimage.cdek.ru\/images\/7271\/20467_image"}},{"@attributes":{"url":"https:\/\/pvzimage.cdek.ru\/images\/7271\/20469_image"}}],"WorkTimeY":[{"@attributes":{"day":"1","periods":"10:00\/20:00"}},{"@attributes":{"day":"2","periods":"10:00\/20:00"}},{"@attributes":{"day":"3","periods":"10:00\/20:00"}},{"@attributes":{"day":"4","periods":"10:00\/20:00"}},{"@attributes":{"day":"5","periods":"10:00\/20:00"}},{"@attributes":{"day":"6","periods":"10:00\/18:00"}},{"@attributes":{"day":"7","periods":"10:00\/18:00"}}]},"6578 Постамат ОМНИСДЭК":{"@attributes":{"Code":"TOM32","Status":"ACTIVE","PostalCode":"634003","Name":"6578 Постамат ОМНИСДЭК","CountryCode":"1","countryCodeIso":"RU","CountryName":"Россия","RegionCode":"53","RegionName":"Томская обл.","CityCode":"269","City":"Томск","WorkTime":"Пн-Вс 10:00-22:00","Address":"АСФАЛЬТОВЫЙ ПЕР, 8","FullAddress":"Россия, Томская обл., Томск, АСФАЛЬТОВЫЙ ПЕР, 8","AddressComment":"Как добраться до ТЦ Клевер: напротив ТЦ Изумрудный Город, остановка Изумрудный город, ТЦ Клевер Цокольный этаж","Phone":"+78007753553","Email":"","Note":"Как добраться до ТЦ Клевер: напротив ТЦ Изумрудный Город, остановка Изумрудный город, ТЦ Клевер Цокольный этаж","coordX":"84.979728","coordY":"56.487245","Type":"POSTAMAT","ownerCode":"cdek","IsDressingRoom":"false","HaveCashless":"true","HaveCash":"false","AllowedCod":"true","TakeOnly":"false","IsHandout":"true","IsReception":"true","NearestStation":"ТРЦ Изумрудный город","MetroStation":"","Site":"","Fulfillment":"false","FiasGuid":"e3b0eae8-a4ce-4779-ae04-5c0797de66be"},"PhoneDetail":{"@attributes":{"number":"+78007753553"}},"OfficeImage":[{"@attributes":{"url":"https:\/\/pvzimage.cdek.ru\/images\/8396\/35324_image"}},{"@attributes":{"url":"https:\/\/pvzimage.cdek.ru\/images\/8396\/35326_image"}},{"@attributes":{"url":"https:\/\/pvzimage.cdek.ru\/images\/8396\/35328_image"}}],"WorkTimeY":[{"@attributes":{"day":"1","periods":"10:00\/22:00"}},{"@attributes":{"day":"2","periods":"10:00\/22:00"}},{"@attributes":{"day":"3","periods":"10:00\/22:00"}},{"@attributes":{"day":"4","periods":"10:00\/22:00"}},{"@attributes":{"day":"5","periods":"10:00\/22:00"}},{"@attributes":{"day":"6","periods":"10:00\/22:00"}},{"@attributes":{"day":"7","periods":"10:00\/22:00"}}],"WeightLimit":{"@attributes":{"WeightMin":"0","WeightMax":"30"}},"Dimensions":{"@attributes":{"depth":"40.5","height":"36.5","width":"64.5"}}},"На Суворова 1А":{"@attributes":{"Code":"TOM41","Status":"ACTIVE","PostalCode":"634062","Name":"На Суворова 1А","CountryCode":"1","countryCodeIso":"RU","CountryName":"Россия","RegionCode":"53","RegionName":"Томская обл.","CityCode":"269","City":"Томск","WorkTime":"Пн-Пт 09:00-20:00, Сб-Вс 10:00-18:00","Address":"ул. Суворова, 1А","FullAddress":"Россия, Томская обл., Томск, ул. Суворова, 1А","AddressComment":"Остановка \"Автодорожный техникум\", автобусные маршруты № 20, 510. Отдельный вход , над входом вывеска \"CDEK\".","Phone":"+79913917370","Email":"s.kazakov@cdek.ru","Note":"Остановка \"Автодорожный техникум\", автобусные маршруты № 20, 510. Отдельный вход , над входом вывеска \"CDEK\".","coordX":"85.027814","coordY":"56.509419","Type":"PVZ","ownerCode":"cdek","IsDressingRoom":"true","HaveCashless":"true","HaveCash":"true","AllowedCod":"true","TakeOnly":"false","IsHandout":"true","IsReception":"true","NearestStation":"Автодорожный техникум","MetroStation":"","Site":"","Fulfillment":"false","FiasGuid":"e3b0eae8-a4ce-4779-ae04-5c0797de66be"},"PhoneDetail":{"@attributes":{"number":"+79913917370"}},"OfficeImage":[{"@attributes":{"url":"https:\/\/pvzimage.cdek.ru\/images\/8931\/44644_image"}},{"@attributes":{"url":"https:\/\/pvzimage.cdek.ru\/images\/8931\/44646_image"}},{"@attributes":{"url":"https:\/\/pvzimage.cdek.ru\/images\/8931\/44648_image"}},{"@attributes":{"url":"https:\/\/pvzimage.cdek.ru\/images\/8931\/44650_image"}},{"@attributes":{"url":"https:\/\/pvzimage.cdek.ru\/images\/8931\/44652_image"}},{"@attributes":{"url":"https:\/\/pvzimage.cdek.ru\/images\/8931\/44654_image"}}],"WorkTimeY":[{"@attributes":{"day":"1","periods":"09:00\/20:00"}},{"@attributes":{"day":"2","periods":"09:00\/20:00"}},{"@attributes":{"day":"3","periods":"09:00\/20:00"}},{"@attributes":{"day":"4","periods":"09:00\/20:00"}},{"@attributes":{"day":"5","periods":"09:00\/20:00"}},{"@attributes":{"day":"6","periods":"10:00\/18:00"}},{"@attributes":{"day":"7","periods":"10:00\/18:00"}}]}}