{"На Дружбы Народов":{"@attributes":{"Code":"NRG3","Status":"ACTIVE","PostalCode":"678960","Name":"На Дружбы Народов","CountryCode":"1","countryCodeIso":"RU","CountryName":"Россия","RegionCode":"10","RegionName":"Саха респ. (Якутия)","CityCode":"892","City":"Нерюнгри","WorkTime":"Пн-Пт 10:00-19:00, Сб 10:00-16:00","Address":"пр. Дружбы Народов, 14\/1","FullAddress":"Россия, Саха респ. (Якутия), Нерюнгри, пр. Дружбы Народов, 14\/1","AddressComment":"пр. Дружбы Народов 14\/1, цокольный этаж.","Phone":"+79248994299, +74114794299","Email":"s.kryuchkov@cdek.ru","Note":"пр. Дружбы Народов 14\/1, цокольный этаж.","coordX":"124.715887","coordY":"56.656767","Type":"PVZ","ownerCode":"cdek","IsDressingRoom":"true","HaveCashless":"true","HaveCash":"true","AllowedCod":"true","TakeOnly":"false","IsHandout":"true","IsReception":"true","NearestStation":"Площадь Ленина","MetroStation":"","Site":"","Fulfillment":"false","FiasGuid":"6ece5c38-f802-4f32-ad33-0409538c3562"},"PhoneDetail":[{"@attributes":{"number":"+79248994299"}},{"@attributes":{"number":"+74114794299"}}],"OfficeImage":[{"@attributes":{"url":"https:\/\/pvzimage.cdek.ru\/images\/2123\/2106_1_NRG3"}},{"@attributes":{"url":"https:\/\/pvzimage.cdek.ru\/images\/2123\/29423_image"}},{"@attributes":{"url":"https:\/\/pvzimage.cdek.ru\/images\/2123\/29425_image"}},{"@attributes":{"url":"https:\/\/pvzimage.cdek.ru\/images\/2123\/29427_image"}},{"@attributes":{"url":"https:\/\/pvzimage.cdek.ru\/images\/2123\/29429_image"}}],"WorkTimeY":[{"@attributes":{"day":"1","periods":"10:00\/19:00"}},{"@attributes":{"day":"2","periods":"10:00\/19:00"}},{"@attributes":{"day":"3","periods":"10:00\/19:00"}},{"@attributes":{"day":"4","periods":"10:00\/19:00"}},{"@attributes":{"day":"5","periods":"10:00\/19:00"}},{"@attributes":{"day":"6","periods":"10:00\/16:00"}}]}}