{"Бульварная":{"@attributes":{"Code":"CHER5","Status":"ACTIVE","PostalCode":"665415","Name":"Бульварная","CountryCode":"1","countryCodeIso":"RU","CountryName":"Россия","RegionCode":"4","RegionName":"Иркутская обл.","CityCode":"2371","City":"Черемхово","WorkTime":"Пн-Пт 09:00-18:00, Сб 10:00-16:00","Address":"ул. Бульварная, 2","FullAddress":"Россия, Иркутская обл., Черемхово, ул. Бульварная, 2","AddressComment":"Расположен ПВЗ в 120 метрах от площади Ленина","Phone":"+79915428007","Email":"e.mironova@cdek.ru","Note":"Расположен ПВЗ в 120 метрах от площади Ленина","coordX":"103.091093","coordY":"53.138186","Type":"PVZ","ownerCode":"cdek","IsDressingRoom":"true","HaveCashless":"true","HaveCash":"true","AllowedCod":"true","TakeOnly":"false","IsHandout":"true","IsReception":"true","NearestStation":"Площадь Ленина","MetroStation":"","Site":"","Fulfillment":"false","FiasGuid":"f05b68c4-f1c7-4c3d-b557-f1f44a57b85f"},"PhoneDetail":{"@attributes":{"number":"+79915428007"}},"OfficeImage":[{"@attributes":{"url":"https:\/\/pvzimage.cdek.ru\/images\/5102\/28821_image"}},{"@attributes":{"url":"https:\/\/pvzimage.cdek.ru\/images\/5102\/28807_image"}},{"@attributes":{"url":"https:\/\/pvzimage.cdek.ru\/images\/5102\/28811_image"}}],"WorkTimeY":[{"@attributes":{"day":"1","periods":"09:00\/18:00"}},{"@attributes":{"day":"2","periods":"09:00\/18:00"}},{"@attributes":{"day":"3","periods":"09:00\/18:00"}},{"@attributes":{"day":"4","periods":"09:00\/18:00"}},{"@attributes":{"day":"5","periods":"09:00\/18:00"}},{"@attributes":{"day":"6","periods":"10:00\/16:00"}}],"WeightLimit":{"@attributes":{"WeightMin":"0","WeightMax":"100"}}}}