{"На Ленина, 72б":{"@attributes":{"Code":"KMN5","Status":"ACTIVE","PostalCode":"658700","Name":"На Ленина, 72б","CountryCode":"1","countryCodeIso":"RU","CountryName":"Россия","RegionCode":"2","RegionName":"Алтайский край","CityCode":"786","City":"Камень-на-Оби","WorkTime":"Пн-Пт 09:00-18:00, Сб 10:00-16:00","Address":"ул. Ленина, 72Б","FullAddress":"Россия, Алтайский край, Камень-на-Оби, ул. Ленина, 72Б","AddressComment":"Главное отделение Сбербанка, отдельный вход слева от главного","Phone":"+79001632353","Email":"ov.bondareva@cdek.ru","Note":"Главное отделение Сбербанка, отдельный вход слева от главного","coordX":"81.3488","coordY":"53.797363","Type":"PVZ","ownerCode":"cdek","IsDressingRoom":"true","HaveCashless":"true","HaveCash":"true","AllowedCod":"true","TakeOnly":"false","IsHandout":"true","IsReception":"true","NearestStation":"Пенсионный фонд","MetroStation":"","Site":"","Fulfillment":"false","FiasGuid":"810ca9c7-f10e-4def-9c48-f0aa83168ca7"},"PhoneDetail":{"@attributes":{"number":"+79001632353"}},"OfficeImage":[{"@attributes":{"url":"https:\/\/pvzimage.cdek.ru\/images\/8136\/32834_image"}},{"@attributes":{"url":"https:\/\/pvzimage.cdek.ru\/images\/8136\/32837_image"}},{"@attributes":{"url":"https:\/\/pvzimage.cdek.ru\/images\/8136\/32840_image"}},{"@attributes":{"url":"https:\/\/pvzimage.cdek.ru\/images\/8136\/32842_image"}}],"WorkTimeY":[{"@attributes":{"day":"1","periods":"09:00\/18:00"}},{"@attributes":{"day":"2","periods":"09:00\/18:00"}},{"@attributes":{"day":"3","periods":"09:00\/18:00"}},{"@attributes":{"day":"4","periods":"09:00\/18:00"}},{"@attributes":{"day":"5","periods":"09:00\/18:00"}},{"@attributes":{"day":"6","periods":"10:00\/16:00"}}],"WeightLimit":{"@attributes":{"WeightMin":"0","WeightMax":"35"}}}}