{"На Лермонтова":{"@attributes":{"Code":"PKHV2","Status":"ACTIVE","PostalCode":"446450","Name":"На Лермонтова","CountryCode":"1","countryCodeIso":"RU","CountryName":"Россия","RegionCode":"57","RegionName":"Самарская обл.","CityCode":"1041","City":"Похвистнево","WorkTime":"Пн-Пт 10:00-19:00, Сб 10:00-16:00","Address":"ул. Лермонтова, 24","FullAddress":"Россия, Самарская обл., Похвистнево, ул. Лермонтова, 24","AddressComment":"","Phone":"+79608252987","Email":"n.kostitsyna@cdek.ru","Note":"","coordX":"52.129811","coordY":"53.657108","Type":"PVZ","ownerCode":"cdek","IsDressingRoom":"true","HaveCashless":"true","HaveCash":"true","AllowedCod":"true","TakeOnly":"false","IsHandout":"true","IsReception":"true","NearestStation":"школа №1","MetroStation":"","Site":"","Fulfillment":"false","FiasGuid":"ddb9cec8-ee07-4788-b80d-39535aea78f9"},"PhoneDetail":{"@attributes":{"number":"+79608252987"}},"OfficeImage":[{"@attributes":{"url":"https:\/\/pvzimage.cdek.ru\/images\/4245\/7033_image"}},{"@attributes":{"url":"https:\/\/pvzimage.cdek.ru\/images\/4245\/7035_image"}},{"@attributes":{"url":"https:\/\/pvzimage.cdek.ru\/images\/4245\/7037_image"}}],"WorkTimeY":[{"@attributes":{"day":"1","periods":"10:00\/19:00"}},{"@attributes":{"day":"2","periods":"10:00\/19:00"}},{"@attributes":{"day":"3","periods":"10:00\/19:00"}},{"@attributes":{"day":"4","periods":"10:00\/19:00"}},{"@attributes":{"day":"5","periods":"10:00\/19:00"}},{"@attributes":{"day":"6","periods":"10:00\/16:00"}}]}}